Workbook
Name _2.1Boholes_and_pump_Stations2: #REF!
Name _B100: #REF!
Name _B100: #REF!
Name _B100: #REF!
Name _B100: #REF!
Name _B100: #REF!
Name _B100000: #REF!
Name _B100000: #REF!
Name _B100000: #REF!
Name _B100000: #REF!
Name _B100000: #REF!
Name _B100000: #REF!
Name _B1000000: #REF!
Name _B1000000: #REF!
Name _B1000000: #REF!
Name _B1000000: #REF!
Name _B1000000: #REF!
Name _B1000000: #REF!
Name _B990000: #REF!
Name _B990000: #REF!
Name _B990000: #REF!
Name _B990000: #REF!
Name _B990000: #REF!
Name a: #REF!
Name aa: #REF!
Name aa: #REF!
Name aa: #REF!
Name aa: #REF!
Name aa: #REF!
Name AB: #REF!
Name AB: #REF!
Name AB: #REF!
Name AB: #REF!
Name AB: #REF!
Name ablution: #REF!
Name ablution: #REF!
Name ablution: #REF!
Name ablution: #REF!
Name ablution: #REF!
Name adaptors: #REF!
Name airvalves: #REF!
Name Anti_termite_treatment: #REF!
Name Anti_termite_treatment: #REF!
Name Anti_termite_treatment: #REF!
Name Anti_termite_treatment: #REF!
Name Anti_termite_treatment: #REF!
Name aqsww: #REF!
Name aqsww: #REF!
Name aqsww: #REF!
Name aqsww: #REF!
Name aqsww: #REF!
Name aserr: #REF!
Name aserr: #REF!
Name aserr: #REF!
Name aserr: #REF!
Name aserr: #REF!
Name Assumed_Yard_Connection_Growth_Rate: #REF!
Name b: #REF!
Name b: #REF!
Name b: #REF!

Sheet Cover Page 
B3: Republic of Uganda
B4: Uganda Police Force
B8: CONSTRUCTION OF THE PROPOSED POLICE CDAC BUILDING AT KIBULI
B14: ESTIMATE BILLS OF QUANTITIES (SCHEME DESIGN STAGE)
D25: FEBRUARY 2025

Sheet Fly Sht. Main Summary
B3: MAIN SUMMARY

Sheet Main Summary
B2: PROJECT: | D2: CONSTRUCTION OF THE PROPOSED POLICE CDAC BUILDING AT KIBULI
B3: EMPLOYER: | D3: UGANDA POLICE FORCE
B4: LOCATION:
B5: DATE: | D5: ='Cover Page '!D25 -> FEBRUARY 2025
B6: MAIN SUMMARY
B8: BILL NO. | D8: DESCRIPTION | F8: PAGE NO. | G8: AMOUNT (USHS.)
B12: 4 | D12: ELECTRICAL INSTALLATIONS | F12: ='Sum. Bill No.4'!C28 -> 4/S | G12: ='Sum. Bill No.4'!E27 -> 1168620150
B13: 5 | D13: MECHANICAL INSTALLATIONS | F13: ='Sum. Bill No.5'!C27 -> 5/S | G13: ='Sum. Bill No.5'!E26 -> 652532100
B14: 6 | D14: ='Sum. Bill No.6'!C5 -> FIRE FIGHTING INSTALLATIONS | F14: ='Sum. Bill No.6'!C27 -> 6/S | G14: ='Sum. Bill No.6'!E26 -> 395471000
B15: 7 | D15: HVAC INSTALLATIONS | F15: ='Sum. Bill No.7'!C25 -> 7/S | G15: ='Sum. Bill No.7'!E24 -> 1.2646556e+09
B16: 8 | D16: LIFT INSTALLATIONS | F16: ='Bill No.8 Lift Inst.'!C38 -> 8/S | G16: ='Bill No.8 Lift Inst.'!G37 -> 356900000
B17: 9 | D17: ICT INSTALLATIONS | F17: ='Sum. Bill No.9'!C25 -> 9/S | G17: ='Sum. Bill No.9'!E24 -> 430266500
D22: SUB-TOTAL 1 | G22: =SUM(G9:G21) -> 4.2684453e+09
D23: ADD: CONTINGENCIES | F23: 0.05 | G23: =G22*F23 -> 2.1342227e+08
D24: SUB-TOTAL 2 | G24: =SUM(G22:G23) -> 4.4818676e+09
D25: ADD: VAT | F25: 0.18 | G25: =G24*F25 -> 8.0673617e+08
D26: TOTAL COST | G26: =SUM(G24:G25) -> 5.2886037e+09 | J26: =G26/0.25 -> 2.1154415e+10
B28: …………………………………….……………… | E28: …………………….………………………. | J28: =J26/3670 -> 5764145.8
B29: Signature of Employer | E29: Signature of the Contractor
B31: Witness: ______________________________ | E31: Witness: ___________________________
B32: ______________________________ | E32: ___________________________
B33: ______________________________ | E33: ___________________________
B35: Date: ………………..……………….. | E35: Date: ………………………………...……….
E37: G/S

Sheet Fly Sht. Main Sum
B2: MAIN SUMMARY

Sheet Main Contract
B2: ITEM | C2: DESCRIPTION | D2: QTY | E2: UNIT | F2: RATE (US$.) | G2: AMOUNT (US$.)
C3: =#REF! -> #REF!
C4: APARTMENTS BLOCK
C5: ELEMENT NO.1
C6: SITE CLEARANCE AND EARTHWORKS
C7: DEMOLITIONS
C8: Carefully demolish and pull down to ground including grubbing up foundations of the following buildings; comprising of: galvanised iron sheet roof covering on existing roof structure, solid walls, concrete floor slab with and including all doors, windows, fittings, electrical and mechanical installations, and including all other existing sundries; allow for keeping andhanding over all salvaged materials to the project manager, or remove from site as directed; make good areas disturbed and remove debris arising from site
B9: A | C9: Building; (Gross floor area Approx. 251SM) | D9: 1 | E9: ITEM | F9: 1631.5 | G9: =F9*D9 -> 1631.5
B10: B | C10: Building; (Gross floor area Approx. 67SM) | D10: 1 | E10: ITEM | F10: 435.5 | G10: =F10*D10 -> 435.5
C11: SITE CLEARANCE
B12: C | C12: Clear site of all trees, bushes, shrubs and under growth including grubbing up roots and removing away from site | D12: 2355 | E12: SM | F12: 0.35 | G12: =F12*D12 -> 824.25
B13: D | C13: Excavate average 200mm deep to remove top soil: remove from site | D13: =D12 -> 2355 | E13: SM | F13: 0.65 | G13: =F13*D13 -> 1530.75
C14: EARTHWORKS
B15: E | C15: Mechanical excavation to reduce levels not exceeding 1.5m deep commencing from stripped level | D15: 3522 | E15: CM | F15: 1.64 | G15: =D15*F15 -> 5776.08
B16: F | C16: Ditto but 1.5 - 3.0 meters deep; | D16: =D15 -> 3522 | E16: CM | F16: 2.05 | G16: =D16*F16 -> 7220.1
C17: DESIGN AND INSTALLATION OF LATERAL SUPPORT
B18: G | C18: Design and install lateral support to the exposed vertical faces of excavation average 3.0m deep and 50m long in confined space from foundations to ground level; all to project manager's approval; | D18: 1 | E18: ITEM | F18: 540 | G18: =F18*D18 -> 540
B19: H | C19: Allow for keeping the whole of the excavation free from general water. | D19: 1 | E19: ITEM | F19: 410 | G19: =F19*D19 -> 410
C20: CART AWAY AND FILLING
B21: I | C21: Load from spoil heaps and and spread on site, compact levelled murram in 150mm thick layers to the Engineer's satisfaction cart away excavated material from site. | D21: 1408 | E21: CM | F21: 2.2 | G21: =D21*F21 -> 3097.6
B22: J | C22: Load from spoil heaps and remove surplus excavated materials from site | D22: 5636 | E22: CM | F22: 4.1 | G22: =D22*F22 -> 23107.6
C24: TO SUMMARY | G24: =SUM(G9:G23) -> 44573.38
C25: 2/1/1
C26: =C3 -> #REF!
C27: =C4 -> APARTMENTS BLOCK
C28: ELEMENT NO.2
C29: RETAINING WALL
B30: A | C30: Allow for maintaining and upholding sides of excavation : clear off all fallen material, rubbish. | D30: 1 | E30: ITEM | F30: INCLUDED
B31: B | C31: Allow for keeping the whole of the excavation free from general water. | D31: 1 | E31: ITEM | F31: INCLUDED
B32: C | C32: Excavate for retaining wall commencing at reduced level but not exceeding 1.5m deep. | D32: 74 | E32: CM | F32: 1.65 | G32: =F32*D32 -> 122.1
B33: D | C33: Extra over excavation for excavating in rock. | D33: 7 | E33: CM | F33: 6.85 | G33: =F33*D33 -> 47.95
B34: E | C34: Return fill and ram selected excavated material around foundations. | D34: 33 | E34: CM | F34: 2.2 | G34: =F34*D34 -> 72.6
B35: F | C35: Load and remove from site surplus excavated materials | D35: 40 | E35: CM | F35: 3.3 | G35: =F35*D35 -> 132
B36: G | C36: Insecticide treatment to bottom of excavation. | D36: 74 | E36: SM | F36: 1.37 | G36: =F36*D36 -> 101.38
C37: CONCRETE WORK
C38: PLAIN CONCRETE CLASS 15 (15Mpa/19mm concrete with 20mm max. aggregate size)
B39: H | C39: 50mm thick blinding layer under retaining wall footings | D39: =D36 -> 74 | E39: SM | F39: 7.25 | G39: =F39*D39 -> 536.5
C40: VIBRATED REINFORCED CONCRETE CLASS 25 (25Mpa/19mm with 20mm max. aggregate size)
B41: I | C41: Retaining wall footings | D41: 26 | E41: CM | F41: 165 | G41: =F41*D41 -> 4290
B42: J | C42: 200mm thick retaining walls | D42: 188 | E42: SM | F42: 33 | G42: =F42*D42 -> 6204
C43: STEEL REINFORCEMENT as described including cutting to length, bending, hoisting and fixing and including all necessary tying wire and spacing blocks
C44: RIBBED BARS to BS 5950
B45: K | C45: 10mm diameter bars | D45: 1188 | E45: KG | F45: 1.35 | G45: =F45*D45 -> 1603.8
B46: L | C46: 12mm diameter bars | D46: 4286 | E46: KG | F46: 1.35 | G46: =F46*D46 -> 5786.1
C47: FORMWORK to;
B48: M | C48: Vertical sides of retaining wall footings | D48: 34 | E48: SM | F48: 9 | G48: =F48*D48 -> 306
B49: N | C49: Vertical sides of retaining walls | D49: =D42*2 -> 376 | E49: SM | F49: 9 | G49: =F49*D49 -> 3384
B50: O | C50: Extra over formwork for fair facing | D50: 150 | E50: SM | F50: 9 | G50: =F50*D50 -> 1350
C51: PREPARE AND APPLY ONE MIST COAT AND THREE COATS silk vinyl emulsion paint internally onto:
B52: P | C52: Fair faced retaining wall surfaces | D52: =D50 -> 150 | E52: SM | F52: 4 | G52: =F52*D52 -> 600
C54: TO COLLECTION | G54: =SUM(G32:G52) -> 24536.43
C55: 2/2/1
C56: TANKING
C57: SIKA CEMFLEX Waterproofing Membrane or other approved equal waterproofing Membrane: applied in accordance with manufacturer's instructions : to
B58: A | C58: Walls : internally | D58: =D42 -> 188 | E58: SM | F58: 16.5 | G58: =F58*D58 -> 3102
B59: B | C59: 40 x 40mm Triangular fillet | D59: 50 | E59: LM | F59: 2.05 | G59: =F59*D59 -> 102.5
B60: C | C60: "Sika Swell" T-Profile joint at junctions of wall and floor | D60: =D59 -> 50 | E60: LM | F60: 3.45 | G60: =F60*D60 -> 172.5
C61: PROTECTIVE LAYER
B62: D | C62: 100mm Thick "Dry stacked" interlocking blocks to vertical sides of retaining wall | D62: =D42 -> 188 | E62: SM | F62: 9.65 | G62: =F62*D62 -> 1814.2
B63: E | C63: 250mm Thick layer of stone sieve, handpacked along the retaining wall | D63: =D62 -> 188 | E63: SM | F63: 6.85 | G63: =F63*D63 -> 1287.8
C64: DRAINAGE
B65: F | C65: 150mm diameter porous PVC pipe lain in granular fill | D65: =D60 -> 50 | E65: LM | F65: 9 | G65: =F65*D65 -> 450
C67: TO COLLECTION | G67: =SUM(G58:G66) -> 6929
C69: COLLECTION
C70: Total carried forward from Page 2/2/1 | G70: =G54 -> 24536.43
C71: Total carried forward from Page 2/2/2 | G71: =G67 -> 6929
C84: TO SUMMARY | G84: =SUM(G70:G83) -> 31465.43
C85: 2/2/2
C86: =C3 -> #REF!
C87: =C4 -> APARTMENTS BLOCK
C88: ELEMENT NO.3
C89: SUBSTRUCTURES
C90: The work in this element includes all works up to and including the ground floor slab
B91: A | C91: Allow for maintaining and upholding sides of excavation : clear off all fallen material, rubbish. | D91: 1 | E91: ITEM | F91: INCLUDED
B92: B | C92: Allow for keeping the whole of the excavation free from general water. | D92: 1 | E92: ITEM | F92: INCLUDED
B93: C | C93: Excavate for column bases commencing at reduced level but not exceeding 1.5m deep. | D93: 1412 | E93: CM | F93: 1.65 | G93: =F93*D93 -> 2329.8
B94: D | C94: Excavate for foundation trench commencing at reduced level but not exceeding 1.5m deep. | D94: 80 | E94: CM | F94: 1.65 | G94: =F94*D94 -> 132
B95: E | C95: Extra over excavation for excavating in rock. | D95: 149 | E95: CM | F95: 6.85 | G95: =F95*D95 -> 1020.65
B96: F | C96: Return fill and ram selected excavated material around foundations. | D96: 687 | E96: CM | F96: 2.2 | G96: =F96*D96 -> 1511.4
B97: G | C97: Load and remove from site surplus excavated materials | D97: 805 | E97: CM | F97: 3.3 | G97: =F97*D97 -> 2656.5
B98: H | C98: Approved murram fill : well compacted in 150mm thick layers. | D98: 761 | E98: CM | F98: 6.56 | G98: =F98*D98 -> 4992.16
B99: I | C99: 150mm Thick Bed of handpacked stone base, well rolled and compacted | D99: 1692 | E99: SM | F99: 8.5 | G99: =F99*D99 -> 14382
B100: J | C100: 50mm thick dust blinding over surfaces of hardcore | D100: =D99 -> 1692 | E100: SM | F100: 1.6 | G100: =F100*D100 -> 2707.2
B101: K | C101: Insecticide treatment to surfaces of hardcore, top of foundation walling and bottom of excavation. | D101: 2737 | E101: SM | F101: 1.37 | G101: =F101*D101 -> 3749.69
C102: CONCRETE WORK
C103: PLAIN CONCRETE CLASS 15 (15Mpa/19mm concrete with 20mm max. aggregate size)
B104: L | C104: 50mm Thick blinding layer under column bases | D104: 941 | E104: SM | F104: 7.25 | G104: =F104*D104 -> 6822.25
C105: MASS CONCRETE CLASS 15 (15Mpa/19mm concrete with 20mm max. aggregate size)
B106: M | C106: Strip foundation | D106: 13 | E106: CM | F106: 145 | G106: =F106*D106 -> 1885
C107: VIBRATED REINFORCED CONCRETE CLASS 30 (30Mpa/19mm with 20mm max. aggregate size)
B108: N | C108: Column bases | D108: 694 | E108: CM | F108: 180 | G108: =F108*D108 -> 124920
B109: O | C109: Columns | D109: 17 | E109: CM | F109: 180 | G109: =F109*D109 -> 3060
B110: P | C110: 150mm thick ground floor slab | D110: 1729 | E110: SM | F110: 27 | G110: =F110*D110 -> 46683
C112: TO COLLECTION | G112: =SUM(G93:G111) -> 216851.65
C113: 2/3/1
C114: SUB-WALLING
C115: Solid Concrete Blockwork of minimum compressive strength of 2.8N/mm2 and mortar designation of (iii) jointed and pointed in cement sand (1:3) mortar : with and including hoop iron wall ties every two courses to BS 1243, 1978: in
B116: A | C116: 200mm Thick walls. | D116: 186 | E116: SM | F116: 24 | G116: =F116*D116 -> 4464
C117: STEEL REINFORCEMENT as described including cutting to length, bending, hoisting and fixing and including all necessary tying wire and spacing blocks
C118: MILD STEEL ROUND BARS TO BS 4449
...

Sheet Fly Sht. Bill No.4
B2: BILL NO.4
B3: ELECTRICAL INSTALLATIONS

Sheet Sum. Bill No.4
B2: ELEMENT | C2: DESCRIPTION | D2: PAGE NO. | E2: AMOUNT (USHS)
C4: ='Fly Sht. Bill No.4'!B2 -> BILL NO.4
C5: ='Fly Sht. Bill No.4'!B3 -> ELECTRICAL INSTALLATIONS
C6: SUMMARY
B7: 1 | C7: LOWER GROUND FLOOR | D7: ='Bill No.4 Electrical Inst.'!C39 -> 4/1/2 | E7: ='Bill No.4 Electrical Inst.'!G38 -> 7461450
B8: 1 | C8: UPPER GROUND FLOOR | D8: ='Bill No.4 Electrical Inst.'!C105 -> 4/2/2 | E8: ='Bill No.4 Electrical Inst.'!G104 -> 60324150
B9: 2 | C9: FIRST FLOOR | D9: ='Bill No.4 Electrical Inst.'!C168 -> 4/3/3 | E9: ='Bill No.4 Electrical Inst.'!G167 -> 89689250
B10: 3 | C10: SECOND FLOOR | D10: ='Bill No.4 Electrical Inst.'!C233 -> 4/4/3 | E10: ='Bill No.4 Electrical Inst.'!G232 -> 94398800
B11: 4 | C11: THIRD FLOOR | D11: ='Bill No.4 Electrical Inst.'!C297 -> 4/5/3 | E11: ='Bill No.4 Electrical Inst.'!G296 -> 88541250
B12: 5 | C12: FOURTH FLOOR | E12: ='Bill No.4 Electrical Inst.'!G360 -> 88541250
B13: 6 | C13: FIFTH FLOOR | E13: ='Bill No.4 Electrical Inst.'!G424 -> 88541250
B14: 7 | C14: ROOF LEVEL | D14: ='Bill No.4 Electrical Inst.'!C463 -> 4/6/2 | E14: ='Bill No.4 Electrical Inst.'!G462 -> 8191600
B15: 8 | C15: MISCELLANEOUS | D15: ='Bill No.4 Electrical Inst.'!C504 -> 4/6/2 | E15: ='Bill No.4 Electrical Inst.'!G503 -> 49848600
B16: 9 | C16: POWER SUPPLY & SWITCHGEAR | D16: ='Bill No.4 Electrical Inst.'!C542 -> 4/7/1 | E16: ='Bill No.4 Electrical Inst.'!G541 -> 280824000
B17: 10 | C17: CABLING | D17: ='Bill No.4 Electrical Inst.'!C599 -> 4/8/3 | E17: ='Bill No.4 Electrical Inst.'!G598 -> 83745000
B18: 11 | C18: STANDBY GENERATOR | D18: ='Bill No.4 Electrical Inst.'!C632 -> 4/9/1 | E18: ='Bill No.4 Electrical Inst.'!G631 -> 160125000
B19: 12 | C19: PV SOLAR SYSTEM | D19: ='Bill No.4 Electrical Inst.'!C671 -> 4/10/1 | E19: ='Bill No.4 Electrical Inst.'!G670 -> 75850000
C27: TOTAL BILL NO.4 CARRIED TO MAIN SUMMARY | E27: =SUM(E8:E26) -> 1168620150
C28: 4/S

Sheet Bill No.4 Electrical Inst.
B2: ITEM | C2: DESCRIPTION | D2: QTY | E2: UNIT | F2: RATE (USHS) | G2: AMOUNT (USHS.)
C3: ='Fly Sht. Bill No.4'!B2 -> BILL NO.4
C4: ='Fly Sht. Bill No.4'!B3 -> ELECTRICAL INSTALLATIONS
C5: ELEMENT NO.1
C6: LOWER GROUND FLOOR
C7: ALL SPECIFIED MATERIALS - GENERAL NOTES
C8: Provide all materials, install, connect and set to work the following all as described in the Specifications and Drawings.
C9: All builder's work required for installation shall be provided for in the prices whether or not specifically measured on described below such shall included all chases, mortices, holes, notches, cutting, plugging making good finishes, painting or repainting etc
B10: A | C10: Lighting points wired by 3x1.5mm2 SC PVC copper cables in 25mm heavy gauge PVC conduit surface/concealed conduit with drops concealed in walls to switch positions complete with MK steel boxes and all accessories. | D10: =SUM(D21:D26) -> 13 | E10: NO | F10: 139050 | G10: =F10*D10 -> 1807650
B11: B | C11: Socket outlet points wired as a ring by 3 x 2.5mm2 SC PVC copper cables in 25mm heavy gauge PVC surface/concealed conduit/trunking complete with boxes for sockets on trunking and all accessories. | D11: 10 | E11: NO | F11: 115850 | G11: =F11*D11 -> 1158500
B12: C | C12: Television outlet points in 25mm heavy gauge PVC conduit concealed in walls complete with MK steel boxes and all accessories. | D12: 1 | E12: NO | F12: 26400 | G12: =F12*D12 -> 26400
B13: D | C13: Fire Alarm points in 25mm heavy gauge PVC surface/concealed conduit complete with all accessories. | D13: 6 | E13: NO | F13: 26400 | G13: =F13*D13 -> 158400
B14: E | C14: CCTV points in 25mm heavy gauge PVC concealed conduit/trunking complete with all accessories. | D14: 2 | E14: NO | F14: 26400 | G14: =F14*D14 -> 52800
B15: G | C15: Public address points in 25mm heavy gauge PVC concealed conduit/trunking complete with all accessories. | D15: 2 | E15: NO | F15: 26400 | G15: =F15*D15 -> 52800
B16: J | C16: Place 50mm diameter PVC pipe sleeves in beams for passing conduits to the Structural Engineer's approval. | D16: 6 | E16: NO | F16: 4950 | G16: =F16*D16 -> 29700
B17: A | C17: Place 100mm diameter PVC pipes in beams for passing AC pipes to the Structural Engineer's approval. | D17: 6 | E17: NO | F17: 6600 | G17: =F17*D17 -> 39600
B18: B | C18: Steel cable tray 600x50mm fixed in cable duct complete with all accessories. | D18: 6 | E18: LM | F18: 148900 | G18: =F18*D18 -> 893400
B19: C | C19: Steel cable tray 300x50mm fixed in cable duct complete with all accessories. | D19: 6 | E19: LM | F19: 99300 | G19: =F19*D19 -> 595800
C20: Lighting Fittings
B21: D | C21: Recessed downlight 15W LED Lamp, 180mm diameter to IP22, complete with DALI Interface as made by Philips or equal approved (Light Type A) | D21: 4 | E21: NO | F21: 87500 | G21: =F21*D21 -> 350000
B22: E | C22: Recessed downlight 15W LED Lamp, 180mm diameter to IP22, complete with emergency unit for 3hours with DALI Interface as made by Philips or equal approved (Light Type AE) | D22: 2 | E22: NO | F22: 134800 | G22: =F22*D22 -> 269600
B23: J | C23: High performance LED 40W recessed modular flat panel 600x600mm, with DALI Interface as made by Philips or equal approved. (Light Type F4) | D23: 3 | E23: NO | F23: 302700 | G23: =F23*D23 -> 908100
B24: K | C24: High performance LED 40W recessed modular flat panel 600x600mm, complete with emergency unit for 3hours with DALI Interface as made by Philips or equal approved. (Light Type F4E) | D24: 1 | E24: NO | F24: 397200 | G24: =F24*D24 -> 397200
B25: F | C25: Ultra-slim white aluminium bodied maintained LED ceiling mounted Emergency EXIT sign, with engraved fire retardant acrylic sign blade, suitable for double sided viewing, with with DALI Interface and 3hour maintained format, to IP20 protection, as Philips or equal approved (Light Type EXIT) | D25: 1 | E25: NO | F25: 85100 | G25: =F25*D25 -> 85100
B26: M | C26: Die-cast aluminium bulkhead with 6W LED lamp and polycarbonate bowl retained by tamper resistant fixings to IP44 as Philips or equal approoved. (Light Type G) For Lift Shaft. | D26: 2 | E26: NO | F26: 106400 | G26: =F26*D26 -> 212800
C27: Light Switches
B28: Q | C28: 6A 1 gang 1 way light switch as CHINT or equal approved complete with all accessories. | D28: 2 | E28: NO | F28: 19850 | G28: =F28*D28 -> 39700
B29: A | C29: 6A 1 gang 2way light switch as CHINT or equal approved complete with all accessories. | D29: 2 | E29: NO | F29: 26450 | G29: =F29*D29 -> 52900
C30: SOCKETS
B31: C | C31: 13A 3pin twin switched socket outlets on wall/trunking as CHINT or equal approved. | D31: 10 | E31: NO | F31: 33100 | G31: =F31*D31 -> 331000
C38: TO SUMMARY | G38: =SUM(G10:G31) -> 7461450
C39: 4/1/2
C40: =C3 -> BILL NO.4
C41: =C4 -> ELECTRICAL INSTALLATIONS
C42: ELEMENT NO.2
C43: UPPER GROUND FLOOR
C44: ALL SPECIFIED MATERIALS - GENERAL NOTES
C45: Provide all materials, install, connect and set to work the following all as described in the Specifications and Drawings.
C46: All builder's work required for installation shall be provided for in the prices whether or not specifically measured on described below such shall included all chases, mortices, holes, notches, cutting, plugging making good finishes, painting or repainting etc
B47: A | C47: Lighting points wired by 3x1.5mm2 SC PVC copper cables in 25mm heavy gauge PVC conduit surface/concealed conduit with drops concealed in walls to switch positions complete with MK steel boxes and all accessories. | D47: =SUM(D78:D90) -> 122 | E47: NO | F47: 139050 | G47: =F47*D47 -> 16964100
B48: B | C48: Socket outlet points wired as a ring by 3 x 2.5mm2 SC PVC copper cables in 25mm heavy gauge PVC surface/concealed conduit/trunking complete with boxes for sockets on trunking and all accessories. | D48: 40 | E48: NO | F48: 115850 | G48: =F48*D48 -> 4634000
B49: C | C49: Television outlet points in 25mm heavy gauge PVC conduit concealed in walls complete with MK steel boxes and all accessories. | D49: 3 | E49: NO | F49: 26400 | G49: =F49*D49 -> 79200
B50: D | C50: Fire Alarm points in 25mm heavy gauge PVC surface/concealed conduit complete with all accessories. | D50: 24 | E50: NO | F50: 26400 | G50: =F50*D50 -> 633600
B51: E | C51: CCTV points in 25mm heavy gauge PVC concealed conduit/trunking complete with all accessories. | D51: 6 | E51: NO | F51: 26400 | G51: =F51*D51 -> 158400
B52: F | C52: Extraction Fan points wired by 3 x 2.5mm2 SC PVC copper cables in 25mm heavy gauge PVC surface/concealed conduit complete with all accessories. | D52: 2 | E52: NO | F52: 115800 | G52: =F52*D52 -> 231600
B53: G | C53: Public address points in 25mm heavy gauge PVC concealed conduit/trunking complete with all accessories. | D53: 12 | E53: NO | F53: 26400 | G53: =F53*D53 -> 316800
B54: H | C54: Cabling from the Rising Busbar 1 (RBB1) to DB102, by 5x35mm2 SC PVC-I Copper cables in PVC duct/Cable trays/surface complete with terminations, glanding, clipping and all accessories. | D54: 15 | E54: LM | F54: 82750 | G54: =F54*D54 -> 1241250
B55: I | C55: 125A 8 way TPN MCB wall mounted surface Distribution Board, complete with integral 160A TPN MCCB incomer, and the following outgoings: 9x32A SPN, 9x20A SPN MCBs, 6x10A SPN MCBs, and all accessories, as made by L & T or equal approved. (DB105 and DB205) | D55: 1 | E55: NO | F55: 1979750 | G55: =F55*D55 -> 1979750
B56: J | C56: Place 50mm diameter PVC pipe sleeves in beams for passing conduits to the Structural Engineer's approval. | D56: 12 | E56: NO | F56: 4950 | G56: =F56*D56 -> 59400
B57: A | C57: Place 100mm diameter PVC pipes in beams for passing AC pipes to the Structural Engineer's approval. | D57: 16 | E57: NO | F57: 6600 | G57: =F57*D57 -> 105600
B58: B | C58: Steel cable tray 600x50mm fixed in cable duct complete with all accessories. | D58: 45 | E58: LM | F58: 148900 | G58: =F58*D58 -> 6700500
B59: C | C59: Steel cable tray 300x50mm fixed in cable duct complete with all accessories. | D59: 24 | E59: LM | F59: 99300 | G59: =F59*D59 -> 2383200
C77: Lighting Fittings
B78: D | C78: Recessed downlight 15W LED Lamp, 180mm diameter to IP22, complete with DALI Interface as made by Philips or equal approved (Light Type A) | D78: 14 | E78: NO | F78: 87500 | G78: =F78*D78 -> 1225000
B79: E | C79: Recessed downlight 15W LED Lamp, 180mm diameter to IP22, complete with emergency unit for 3hours with DALI Interface as made by Philips or equal approved (Light Type AE) | D79: 6 | E79: NO | F79: 134800 | G79: =F79*D79 -> 808800
B80: F | C80: Ultra-slim white aluminium bodied maintained LED ceiling mounted Emergency EXIT sign, with engraved fire retardant acrylic sign blade, suitable for double sided viewing, with with DALI Interface and 3hour maintained format, to IP20 protection, as Philips or equal approved (Light Type EXIT) | D80: 3 | E80: NO | F80: 85100 | G80: =F80*D80 -> 255300
B81: G | C81: T8 1x20W 1200mm single surface mounted bare batten LED luminaire with DALI Interface as made by Philips or equal approved (Light Type F1). | D81: 30 | E81: NO | F81: 80400 | G81: =F81*D81 -> 2412000
B82: H | C82: T8 1x20W 1200mm single surface mounted bare batten LED luminaire with Emergency 3 hour battery with self test or addressable testing capabilities, with DALI Interface as made by Philips or equal approved (Light Type F1E). | D82: 5 | E82: NO | F82: 106400 | G82: =F82*D82 -> 532000
B83: I | C83: Circular fitting 180mm diameter with 15W LED lamp and polycarbonate bowl retained by tamper resistant fixings to IP44 as Philips or equal approoved. (Light Type B) | D83: 25 | E83: NO | F83: 52500 | G83: =F83*D83 -> 1312500
B84: I | C84: Circular fitting 180mm diameter with 15W LED lamp complete with emergency unit for 3hours and polycarbonate bowl retained by tamper resistant fixings to IP44 as Philips or equal approoved. (Light Type BE) | D84: 4 | E84: NO | F84: 52500 | G84: =F84*D84 -> 210000
B85: J | C85: High performance LED 40W recessed modular flat panel 600x600mm, with DALI Interface as made by Philips or equal approved. (Light Type F4) | D85: 11 | E85: NO | F85: 302700 | G85: =F85*D85 -> 3329700
B86: K | C86: High performance LED 40W recessed modular flat panel 600x600mm, complete with emergency unit for 3hours with DALI Interface as made by Philips or equal approved. (Light Type F4E) | D86: 7 | E86: NO | F86: 397200 | G86: =F86*D86 -> 2780400
B87: L | C87: 20W LED up and down lighter wall mounted luminaire to IP22 as made by Phillips or equal approved (Light type T) | D87: 9 | E87: NO | F87: 124550 | G87: =F87*D87 -> 1120950
B88: M | C88: Die-cast aluminium recessed downlight 15W LED Lamp, 180mm diameter to IP22, complete with DALI Interface as made by Philips or equal approved (Light Type C) | D88: 3 | E88: NO | F88: 106400 | G88: =F88*D88 -> 319200
B89: N | C89: Die-cast aluminium recessed downlight 15W LED Lamp, 200mm diameter to IP22, complete with emergency unit for 3hours with DALI Interface as made by Philips or equal approved (Light Type CE) | D89: 3 | E89: NO | F89: 147500 | G89: =F89*D89 -> 442500
B90: I | C90: Die-cast aluminium bulkhead with 6W LED lamp and polycarbonate bowl retained by tamper resistant fixings to IP44 as Philips or equal approoved. (Light Type G) For Lift Shaft. | D90: 2 | E90: NO | F90: 52500 | G90: =F90*D90 -> 105000
C91: Light Switches
B92: Q | C92: 6A 1 gang 1 way light switch as CHINT or equal approved complete with all accessories. | D92: 12 | E92: NO | F92: 19850 | G92: =F92*D92 -> 238200
B93: A | C93: 6A 1 gang 2way light switch as CHINT or equal approved complete with all accessories. | D93: 8 | E93: NO | F93: 26450 | G93: =F93*D93 -> 211600
B94: B | C94: 10A 3x3 grid 2 way light switch as Legrand or equal approved complete with all accessories. | D94: 2 | E94: NO | F94: 397200 | G94: =F94*D94 -> 794400
C95: SOCKETS
B96: C | C96: 13A 3pin twin switched socket outlets on wall/trunking as CHINT or equal approved. | D96: 40 | E96: NO | F96: 33100 | G96: =F96*D96 -> 1324000
B97: D | C97: Automatic HAND DRYER as STARMIX model no : T7E Electronic or equal approved complete with all accessories. | D97: 8 | E97: NO | F97: 794500 | G97: =F97*D97 -> 6356000
B98: E | C98: DP points wired by 3x2.5mm2 SC PVC copper cables in 25mm heavy gauge PVC surface/concealed conduit complete with all accessories. | D98: 8 | E98: NO | F98: 132400 | G98: =F98*D98 -> 1059200
C104: TO SUMMARY | G104: =SUM(G47:G98) -> 60324150
C105: 4/2/2
C106: =C3 -> BILL NO.4
C107: =C4 -> ELECTRICAL INSTALLATIONS
C108: ELEMENT NO.3
C109: FIRST FLOOR
B110: A | C110: Lighting points wired by 3x1.5mm2 SC PVC copper cables in 25mm heavy gauge PVC conduit surface/concealed conduit with drops concealed in walls to switch positions complete with MK steel boxes and all accessories. | D110: =SUM(D130:D144) -> 129 | E110: NO | F110: 139050 | G110: =F110*D110 -> 17937450
B111: B | C111: Socket outlet points wired as a ring by 3 x 2.5mm2 SC PVC copper cables in 25mm heavy gauge PVC surface/concealed conduit/trunking complete with boxes for sockets on trunking and all accessories. | D111: 40 | E111: NO | F111: 115800 | G111: =F111*D111 -> 4632000
B112: C | C112: Air Conditioning Indoor Units points wired by 3x2.5mm2 SC PVC copper cables in 25mm heavy gauge PVC surface/concealed conduit complete with all accessories. | D112: 12 | E112: NO | F112: 115800 | G112: =F112*D112 -> 1389600
B113: D | C113: Television outlet points in 25mm heavy gauge PVC conduit concealed in walls complete with MK steel boxes and all accessories. | D113: 2 | E113: NO | F113: 26400 | G113: =F113*D113 -> 52800
B114: E | C114: Fire Alarm points in 25mm heavy gauge PVC surface/concealed conduit complete with all accessories. | D114: 18 | E114: NO | F114: 26400 | G114: =F114*D114 -> 475200
B115: F | C115: Public Address points in 25mm heavy gauge PVC concealed conduit/trunking complete with all accessories. | D115: 12 | E115: NO | F115: 26400 | G115: =F115*D115 -> 316800
B116: G | C116: CCTV points in 25mm heavy gauge PVC concealed conduit/trunking complete with all accessories. | D116: 5 | E116: NO | F116: 26400 | G116: =F116*D116 -> 132000
B117: H | C117: Access control points in 25mm heavy gauge PVC concealed conduit/trunking complete with all accessories. | D117: 6 | E117: NO | F117: 26400 | G117: =F117*D117 -> 158400
B118: I | C118: Extraction Fan points wired by 3 x 2.5mm2 SC PVC copper cables in 25mm heavy gauge PVC surface/concealed conduit complete with all accessories. | D118: 4 | E118: NO | F118: 115800 | G118: =F118*D118 -> 463200
B119: J | C119: Cabling from the Rising Busbar 1 (RBB1) to DB104, by 5x35mm2 SC PVC-I Copper cables in PVC duct/Cable trays/surface complete with terminations, glanding, clipping and all accessories. | D119: 15 | E119: LM | F119: 82700 | G119: =F119*D119 -> 1240500
B120: K | C120: Cabling from the Rising Busbar 1 (RBB1) to DB204, by 5x35mm2 SC PVC-I Copper cables in PVC duct/Cable trays/surface complete with terminations, glanding, clipping and all accessories. | D120: 25 | E120: LM | F120: 82700 | G120: =F120*D120 -> 2067500
B121: L | C121: Cabling from the Rising Busbar 2 (RBB2) to DB304, by 5x35mm2 SC PVC-I Copper cables in PVC duct/Cable trays/surface complete with terminations, glanding, clipping and all accessories. | D121: 15 | E121: LM | F121: 82700 | G121: =F121*D121 -> 1240500
B122: M | C122: 125A 8 way TPN MCB wall mounted surface Distribution Board, complete with integral 125A TPN MCCB incomer, and the following outgoings: 9x32A SPN, 9x20A SPN MCBs, 6x10A SPN MCBs, and all accessories, as made by L & T or equal approved. (DB105 and DB205) | D122: 3 | E122: NO | F122: 1979700 | G122: =F122*D122 -> 5939100
... B128: E | C128: Galvanised Steel cable tray 300x50mm fixed in cable duct complete with all accessories. | D128: 24 | E128: LM | F128: 82750 | G128: =F128*D128 -> 1986000
C129: Lighting Fittings
B130: D | C130: Recessed downlight 15W LED Lamp, 180mm diameter to IP22, complete with DALI Interface as made by Philips or equal approved (Light Type A) | D130: 18 | E130: NO | F130: 87500 | G130: =F130*D130 -> 1575000
B131: E | C131: Recessed downlight 15W LED Lamp, 180mm diameter to IP22, complete with emergency unit for 3hours with DALI Interface as made by Philips or equal approved (Light Type AE) | D131: 7 | E131: NO | F131: 134800 | G131: =F131*D131 -> 943600
B132: F | C132: Ultra-slim white aluminium bodied maintained LED ceiling mounted Emergency EXIT sign, with engraved fire retardant acrylic sign blade, suitable for double sided viewing, with with DALI Interface and 3hour maintained format, to IP20 protection, as Philips or equal approved (Light Type EXIT) | D132: 3 | E132: NO | F132: 85100 | G132: =F132*D132 -> 255300
B133: G | C133: T8 1x20W 1200mm single surface mounted bare batten LED luminaire with DALI Interface as made by Philips or equal approved (Light Type F1). | D133: 0 | E133: NO | F133: 80400 | G133: =F133*D133 -> 0
B134: H | C134: T8 1x20W 1200mm single surface mounted bare batten LED luminaire with Emergency 3 hour battery with self test or addressable testing capabilities, with DALI Interface as made by Philips or equal approved (Light Type F1E). | D134: 0 | E134: NO | F134: 106400 | G134: =F134*D134 -> 0
...

Sheet Fly Sht. Bill No.5
B2: BILL NO.5
B3: MECHANICAL INSTALLATIONS

Sheet Sum. Bill No.5
B2: ELEMENT | C2: DESCRIPTION | D2: PAGE NO. | E2: AMOUNT (USHS)
C4: ='Fly Sht. Bill No.5'!B2 -> BILL NO.5
C5: ='Fly Sht. Bill No.5'!B3 -> MECHANICAL INSTALLATIONS
C6: SUMMARY
B7: 1 | C7: GROUND FLOOR | D7: ='Bill No.5 Mechanical Inst.'!C72 -> 5/1/3 | E7: ='Bill No.5 Mechanical Inst.'!G71 -> 62234200
B8: 2 | C8: FIRST FLOOR | D8: ='Bill No.5 Mechanical Inst.'!C148 -> 5/2/3 | E8: ='Bill No.5 Mechanical Inst.'!G147 -> 66296800
B9: 3 | C9: SECOND FLOOR | D9: ='Bill No.5 Mechanical Inst.'!C227 -> 5/3/3 | E9: ='Bill No.5 Mechanical Inst.'!G226 -> 60496300
B10: 4 | C10: THIRD FLOOR | D10: ='Bill No.5 Mechanical Inst.'!C303 -> 5/4/3 | E10: ='Bill No.5 Mechanical Inst.'!G302 -> 66339600
B11: 6 | C11: FOURTH FLOOR | E11: ='Bill No.5 Mechanical Inst.'!G378 -> 66339600
B12: 7 | C12: FIFTH FLOOR | E12: ='Bill No.5 Mechanical Inst.'!G429 -> 73357800
B13: 8 | C13: WATER SUPPLY | D13: ='Bill No.5 Mechanical Inst.'!C453 -> 5/6/1 | E13: ='Bill No.5 Mechanical Inst.'!G452 -> 150500000
B14: 9 | C14: SEWER SYSTEM | D14: ='Bill No.5 Mechanical Inst.'!C470 -> 5/7/1 | E14: ='Bill No.5 Mechanical Inst.'!G469 -> 66879000
B15: 810 | C15: STORMWATER DISPOSAL | D15: ='Bill No.5 Mechanical Inst.'!C492 -> 5/8/1 | E15: ='Bill No.5 Mechanical Inst.'!G491 -> 40088800
C26: TOTAL BILL NO.5 CARRIED TO MAIN SUMMARY | E26: =SUM(E7:E25) -> 652532100
C27: 5/S

Sheet Bill No.5 Mechanical Inst.
B2: ITEM | C2: DESCRIPTION | D2: QTY | E2: UNIT | F2: RATE (USHS) | G2: AMOUNT (USHS.)
C3: BILL NO.5
C4: MECHANICAL INSTALLATIONS
C5: ELEMENT NO.1
C6: UPPER GROUND FLOOR
C7: Provide all materials, install, connect and set to work the following all as described in the Specifications and Drawings.
C8: All builder's work required for installation shall be provided for in the prices whether or not specifically measured on described below such shall included all chases, mortices, holes, notches, cutting, plugging making good finishes, painting or repainting etc
C9: Sanitary Fittings
B10: A | C10: "Roca Victoria " BTW WC pan for flush valve, white colour, vitreous china to BS3402 with horizontal outlet complete with WC pan with fixing kit and WC inlet connector, removable plastic seat and cover with self closing system. | D10: 10 | E10: NO | F10: 678700 | G10: =F10*D10 -> 6787000
B11: B | C11: Concealed Flush valve for above WC Pan as DOCOL 1-1/4" back entry type, with integral vacuum break, non-hold-open feature and non-return valve, inlet control stop and wall plate complete with all accessories, as DOCOL or equal approved. | D11: 10 | E11: NO | F11: 595900 | G11: =F11*D11 -> 5959000
B12: C | C12: 530x450mm Countertop Vitreous China Wash Hand Basin, with one tap hole 38mm chrome plated chain waste, plastic bottle trap, complete with all accessories as Ideal Standard tempo 53 or equal approved. | D12: 8 | E12: NO | F12: 678700 | G12: =F12*D12 -> 5429600
B13: D | C13: Hands free electronic control pillar tap, single temperature 1/2" BSP F1 complete with pillar tap, mounting kit, solenoid valve as Cobratron EL-JOE by COBRA. | D13: 8 | E13: NO | F13: 347600 | G13: =F13*D13 -> 2780800
B14: E | C14: Mains power supply for electronic tap as EL-Trans Cobratron Transformer 10 Channel mains power supply unit, 220V AC to 9V DC | D14: 8 | E14: NO | F14: 264800 | G14: =F14*D14 -> 2118400
B15: F | C15: Vitreous China semi-recessed toilet roll holder complete with fixing to the wall as Armitage Shanks Mayfair S5009 or equal approved. | D15: 12 | E15: NO | F15: 82700 | G15: =F15*D15 -> 992400
B16: G | C16: Vitreous China Urinal Bowl complete with 38mm chrome plated waste, for flush valve fittings complete with all accessories, as Armitage Shanks Contour S6110 or equal approved. | D16: 4 | E16: NO | F16: 314500 | G16: =F16*D16 -> 1258000
B17: H | C17: Urinal proximity sensor surface mounted complete with solenoid, combined servicing valve and filter, float switch with 10metre extension cable and all accessories as Armitage Shanks Urinal proximity sensor S8116 or equal approved. | D17: 4 | E17: NO | F17: 331000 | G17: =F17*D17 -> 1324000
B18: A | C18: Vitreous China Urinal Bowl separator complete with all accessories, as Armitage Shanks S6120 or equal approved. | D18: 2 | E18: NO | F18: 198600 | G18: =F18*D18 -> 397200
B19: B | C19: 6mm glass plate mirror size 610x475mm with bevelled edges complete. | D19: 8 | E19: NO | F19: 82700 | G19: =F19*D19 -> 661600
B20: C | C20: PWD Suite with Vitreous China low level, with 6no Grab rails in powder coated aluminium and P outlet 6 litre cistern, valve fittings complete with seat and cover and all accessories, with washbasin and non-concussive tap, bottle trap and all accessories as Armitage Shanks Standard Pack S687501 or equal approved. | D20: 2 | E20: NO | F20: 5959450 | G20: =F20*D20 -> 11918900
B21: D | C21: Cleaner's sink in fireclay 510x380mm with splash back, grating complete with Nimbus bib tap and all accessories as Armitage Shanks Alder S5900 or equal approved.. | D21: 2 | E21: NO | F21: 1059450 | G21: =F21*D21 -> 2118900
... B23: F | C23: Pressure type under sink water heater 35litres with glass lining complete with all accessories as Ariston or equal approved for Kitchen. | D23: 2 | E23: NO | F23: 645600 | G23: =F23*D23 -> 1291200
C24: Internal Plumbing
C25: All pipe work shall be PPR PN25, all diameters below are outer diameter and shall be complete with fittings such as bends elbows, tees and all accessories and shall be inclusive of all builder's work.
B26: G | C26: 100mm Pipe work complete. | D26: 8 | E26: LM | F26: 115800 | G26: =F26*D26 -> 926400
B27: H | C27: 100x50mm saddle clamp complete | D27: 2 | E27: NO | F27: 43000 | G27: =F27*D27 -> 86000
B28: I | C28: 80mm Pipe work complete. | D28: 12 | E28: LM | F28: 43000 | G28: =F28*D28 -> 516000
B29: J | C29: 65mm Pipe work complete. | D29: 12 | E29: LM | F29: 36400 | G29: =F29*D29 -> 436800
B30: K | C30: 50mm Pipe work complete. | D30: 48 | E30: LM | F30: 43000 | G30: =F30*D30 -> 2064000
B31: L | C31: 40mm Pipe work complete. | D31: 60 | E31: LM | F31: 36400 | G31: =F31*D31 -> 2184000
B32: M | C32: 32mm Pipe work complete. | D32: 54 | E32: LM | F32: 29700 | G32: =F32*D32 -> 1603800
B33: N | C33: 25mm Pipe work complete. | D33: 48 | E33: LM | F33: 23100 | G33: =F33*D33 -> 1108800
B34: O | C34: 20mm Pipe work complete. | D34: 60 | E34: LM | F34: 13200 | G34: =F34*D34 -> 792000
B35: P | C35: 80mm globe valves | D35: 2 | E35: NO | F35: 165500 | G35: =F35*D35 -> 331000
B36: Q | C36: 65mm globe valves | D36: 2 | E36: NO | F36: 109250 | G36: =F36*D36 -> 218500
B37: R | C37: 50mm globe valves | D37: 4 | E37: NO | F37: 165500 | G37: =F37*D37 -> 662000
... B42: A | C42: 13mm stainless steel braided tubing 300mm long including unions and jointing to steel pipes. | D42: 20 | E42: NO | F42: 16550 | G42: =F42*D42 -> 331000
C43: Foul Water
C44: Supply and fix the following in PVC soil and waste system to BS 4514 with fittings, fixed according to the manufacturer's printed instructions and BS 5572:1978 all as supplied by KEY-TERRAIN or equal, complete with all fittings and accessories.
B45: B | C45: 160mm PVC soil waste pipe on wall and or in duct. | D45: 18 | E45: LM | F45: 82700 | G45: =F45*D45 -> 1488600
B46: C | C46: 110m PVC soil waste pipe on wall and or in duct. | D46: 28 | E46: LM | F46: 59500 | G46: =F46*D46 -> 1666000
B47: D | C47: 50mm PVC soil waste pipe on wall, in wall and or in duct. | D47: 48 | E47: LM | F47: 26400 | G47: =F47*D47 -> 1267200
B48: E | C48: 38mm PVC soil waste pipe on wall, in wall and or in duct. | D48: 24 | E48: LM | F48: 16550 | G48: =F48*D48 -> 397200
B49: F | C49: KEY-TERRAIN Floor traps | D49: 6 | E49: NO | F49: 82700 | G49: =F49*D49 -> 496200
C71: TO SUMMARY | G71: =SUM(G10:G51) -> 62234200
C72: 5/1/3
C73: BILL NO.5
C74: MECHANICAL INSTALLATIONS
C75: ELEMENT NO.2
C76: FIRST FLOOR
C77: Sanitary Fittings
B78: A | C78: "Roca Victoria " BTW WC pan for flush valve, white colour, vitreous china to BS3402 with horizontal outlet complete with WC pan with fixing kit and WC inlet connector, removable plastic seat and cover with self closing system. | D78: 10 | E78: NO | F78: 678700 | G78: =F78*D78 -> 6787000
B79: B | C79: Concealed Flush valve for above WC Pan as DOCOL 1-1/4" back entry type, with integral vacuum break, non-hold-open feature and non-return valve, inlet control stop and wall plate complete with all accessories, as DOCOL or equal approved. | D79: 10 | E79: NO | F79: 595900 | G79: =F79*D79 -> 5959000
B80: C | C80: 530x450mm Countertop Vitreous China Wash Hand Basin, with one tap hole 38mm chrome plated chain waste, plastic bottle trap, complete with all accessories as Ideal Standard tempo 53 or equal approved. | D80: 8 | E80: NO | F80: 678700 | G80: =F80*D80 -> 5429600
B81: D | C81: Hands free electronic control pillar tap, single temperature 1/2" BSP F1 complete with pillar tap, mounting kit, solenoid valve as Cobratron EL-JOE by COBRA. | D81: 8 | E81: NO | F81: 347600 | G81: =F81*D81 -> 2780800
B82: E | C82: Mains power supply for electronic tap as EL-Trans Cobratron Transformer 10 Channel mains power supply unit, 220V AC to 9V DC | D82: 8 | E82: NO | F82: 264800 | G82: =F82*D82 -> 2118400
B83: F | C83: Vitreous China semi-recessed toilet roll holder complete with fixing to the wall as Armitage Shanks Mayfair S5009 or equal approved. | D83: 10 | E83: NO | F83: 82700 | G83: =F83*D83 -> 827000
B84: G | C84: Vitreous China Urinal Bowl complete with 38mm chrome plated waste, for flush valve fittings complete with all accessories, as Armitage Shanks Contour S6110 or equal approved. | D84: 4 | E84: NO | F84: 314500 | G84: =F84*D84 -> 1258000
B85: H | C85: Urinal proximity sensor surface mounted complete with solenoid, combined servicing valve and filter, float switch with 10metre extension cable and all accessories as Armitage Shanks Urinal proximity sensor S8116 or equal approved. | D85: 4 | E85: NO | F85: 331000 | G85: =F85*D85 -> 1324000
B86: I | C86: Vitreous China Urinal Bowl separator complete with all accessories, as Armitage Shanks S6120 or equal approved. | D86: 2 | E86: NO | F86: 198600 | G86: =F86*D86 -> 397200
B87: J | C87: 6mm glass plate mirror size 610x475mm with bevelled edges complete. | D87: 8 | E87: NO | F87: 82700 | G87: =F87*D87 -> 661600
B90: A | C90: PWD Suite with Vitreous China low level, with 6no Grab rails in powder coated aluminium and P outlet 6 litre cistern, valve fittings complete with seat and cover and all accessories, with washbasin and non-concussive tap, bottle trap and all accessories as Armitage Shanks Standard Pack S687501 or equal approved. | D90: 2 | E90: NO | F90: 5959450 | G90: =F90*D90 -> 11918900
B91: B | C91: Cleaner's sink in fireclay 510x380mm with splash back, grating complete with Nimbus bib tap and all accessories as Armitage Shanks Alder S5900 or equal approved.. | D91: 2 | E91: NO | F91: 1059450 | G91: =F91*D91 -> 2118900
... B95: D | C95: 60litre water heater with 3KW electric elemeeeent as ARISTON or equal approved.. | D95: 1 | E95: NO | F95: 1645600 | G95: =F95*D95 -> 1645600
C96: Internal Plumbing
C97: All pipe work shall be PPR PN25, all diameters below are outer diameter and shall be complete with fittings such as bends elbows, tees and all accessories and shall be inclusive of all builder's work.
B98: E | C98: 100mm Pipe work complete. | D98: 8 | E98: LM | F98: 115800 | G98: =F98*D98 -> 926400
B99: F | C99: 100x50mm saddle clamp complete | D99: 2 | E99: NO | F99: 43000 | G99: =F99*D99 -> 86000
B100: G | C100: 80mm Pipe work complete. | D100: 12 | E100: LM | F100: 43000 | G100: =F100*D100 -> 516000
B101: H | C101: 65mm Pipe work complete. | D101: 12 | E101: LM | F101: 36400 | G101: =F101*D101 -> 436800
B102: I | C102: 50mm Pipe work complete. | D102: 48 | E102: LM | F102: 43000 | G102: =F102*D102 -> 2064000
B103: J | C103: 40mm Pipe work complete. | D103: 60 | E103: LM | F103: 36400 | G103: =F103*D103 -> 2184000
B104: K | C104: 32mm Pipe work complete. | D104: 54 | E104: LM | F104: 29700 | G104: =F104*D104 -> 1603800
B105: L | C105: 25mm Pipe work complete. | D105: 48 | E105: LM | F105: 23100 | G105: =F105*D105 -> 1108800
B106: M | C106: 20mm Pipe work complete. | D106: 60 | E106: LM | F106: 13200 | G106: =F106*D106 -> 792000
B107: N | C107: 80mm globe valves | D107: 2 | E107: NO | F107: 165500 | G107: =F107*D107 -> 331000
B108: O | C108: 65mm globe valves | D108: 2 | E108: NO | F108: 109250 | G108: =F108*D108 -> 218500
B109: P | C109: 50mm globe valves | D109: 4 | E109: NO | F109: 165500 | G109: =F109*D109 -> 662000
... B114: U | C114: 13mm stainless steel braided tubing 300mm long including unions and jointing to steel pipes. | D114: 20 | E114: NO | F114: 16550 | G114: =F114*D114 -> 331000
C118: Foul Water
C119: Supply and fix the following in PVC soil and waste system to BS 4514 with fittings, fixed according to the manufacturer's printed instructions and BS 5572:1978 all as supplied by KEY-TERRAIN or equal, complete with all fittings and accessories.
B120: A | C120: 160mm PVC soil waste pipe on wall and or in duct. | D120: 18 | E120: LM | F120: 82700 | G120: =F120*D120 -> 1488600
B121: B | C121: 110m PVC soil waste pipe on wall and or in duct. | D121: 28 | E121: LM | F121: 59500 | G121: =F121*D121 -> 1666000
B122: C | C122: 50mm PVC soil waste pipe on wall, in wall and or in duct. | D122: 48 | E122: LM | F122: 26400 | G122: =F122*D122 -> 1267200
B123: D | C123: 38mm PVC soil waste pipe on wall, in wall and or in duct. | D123: 24 | E123: LM | F123: 16550 | G123: =F123*D123 -> 397200
B124: E | C124: KEY-TERRAIN Floor traps | D124: 6 | E124: NO | F124: 82700 | G124: =F124*D124 -> 496200
C147: TO SUMMARY | G147: =SUM(G78:G125) -> 66296800
C148: 5/2/3
C149: BILL NO.5
C150: MECHANICAL INSTALLATIONS
C151: ELEMENT NO.3
C152: SECOND FLOOR
C153: Sanitary Fittings
B154: A | C154: "Roca Victoria " BTW WC pan for flush valve, white colour, vitreous china to BS3402 with horizontal outlet complete with WC pan with fixing kit and WC inlet connector, removable plastic seat and cover with self closing system. | D154: 10 | E154: NO | F154: 678700 | G154: =F154*D154 -> 6787000
B155: B | C155: Concealed Flush valve for above WC Pan as DOCOL 1-1/4" back entry type, with integral vacuum break, non-hold-open feature and non-return valve, inlet control stop and wall plate complete with all accessories, as DOCOL or equal approved. | D155: 10 | E155: NO | F155: 595900 | G155: =F155*D155 -> 5959000
B156: C | C156: 530x450mm Countertop Vitreous China Wash Hand Basin, with one tap hole 38mm chrome plated chain waste, plastic bottle trap, complete with all accessories as Ideal Standard tempo 53 or equal approved. | D156: 8 | E156: NO | F156: 678700 | G156: =F156*D156 -> 5429600
B157: D | C157: Hands free electronic control pillar tap, single temperature 1/2" BSP F1 complete with pillar tap, mounting kit, solenoid valve as Cobratron EL-JOE by COBRA. | D157: 8 | E157: NO | F157: 347600 | G157: =F157*D157 -> 2780800
B158: E | C158: Mains power supply for electronic tap as EL-Trans Cobratron Transformer 10 Channel mains power supply unit, 220V AC to 9V DC | D158: 8 | E158: NO | F158: 264800 | G158: =F158*D158 -> 2118400
B159: F | C159: Vitreous China semi-recessed toilet roll holder complete with fixing to the wall as Armitage Shanks Mayfair S5009 or equal approved. | D159: 10 | E159: NO | F159: 82700 | G159: =F159*D159 -> 827000
B160: G | C160: Vitreous China Urinal Bowl complete with 38mm chrome plated waste, for flush valve fittings complete with all accessories, as Armitage Shanks Contour S6110 or equal approved. | D160: 2 | E160: NO | F160: 314500 | G160: =F160*D160 -> 629000
B161: H | C161: Concealed type touch-free electronic control Urinal flush valve with manual override complete with all accessories as Conra EL-3006 or equal approved. | D161: 2 | E161: NO | F161: 331000 | G161: =F161*D161 -> 662000
...

Sheet Fly Sht. Bill No.6
B2: BILL NO.6
B3: FIRE FIGHTING INSTALLATIONS

Sheet Sum. Bill No.6
B2: ELEMENT | C2: DESCRIPTION | D2: PAGE NO. | E2: AMOUNT (USHS)
C4: ='Fly Sht. Bill No.6'!B2 -> BILL NO.6
C5: ='Fly Sht. Bill No.6'!B3 -> FIRE FIGHTING INSTALLATIONS
C6: SUMMARY
B7: 1 | C7: ='Bill No.6 Fire fighting Inst.'!C8 -> UPPER GROUND FLOOR | D7: ='Bill No.6 Fire fighting Inst.'!C35 -> 6/1/2 | E7: ='Bill No.6 Fire fighting Inst.'!G34 -> 38979500
B8: 2 | C8: ='Bill No.6 Fire fighting Inst.'!C39 -> FIRST FLOOR | D8: ='Bill No.6 Fire fighting Inst.'!C64 -> 6/2/1 | E8: ='Bill No.6 Fire fighting Inst.'!G63 -> 38979500
B9: 3 | C9: ='Bill No.6 Fire fighting Inst.'!C68 -> SECOND FLOOR | D9: ='Bill No.6 Fire fighting Inst.'!C93 -> 6/3/1 | E9: ='Bill No.6 Fire fighting Inst.'!G92 -> 38979500
B10: 4 | C10: ='Bill No.6 Fire fighting Inst.'!C97 -> THIRD FLOOR | D10: ='Bill No.6 Fire fighting Inst.'!C122 -> 6/4/1 | E10: ='Bill No.6 Fire fighting Inst.'!G121 -> 38979500
C11: FOURTH FLOOR | E11: ='Bill No.6 Fire fighting Inst.'!G150 -> 38979500
C12: FIFTH FLOOR | E12: ='Bill No.6 Fire fighting Inst.'!G179 -> 38979500
B13: 5 | C13: ='Bill No.6 Fire fighting Inst.'!C184 -> ROOF | D13: ='Bill No.6 Fire fighting Inst.'!C205 -> 6/5/1 | E13: ='Bill No.6 Fire fighting Inst.'!G204 -> 8442000
B14: 6 | C14: ='Bill No.6 Fire fighting Inst.'!C209 -> FIRE FIGHTING EQUIPMENT | D14: ='Bill No.6 Fire fighting Inst.'!C250 -> 6/6/1 | E14: ='Bill No.6 Fire fighting Inst.'!G249 -> 119320000
B15: 7 | C15: ='Bill No.6 Fire fighting Inst.'!C254 -> MISCELLANEOUS | D15: ='Bill No.6 Fire fighting Inst.'!C322 -> 6/7/1 | E15: ='Bill No.6 Fire fighting Inst.'!G321 -> 33832000
C26: TOTAL BILL NO.6 CARRIED TO MAIN SUMMARY | E26: =SUM(E7:E25) -> 395471000
C27: 6/S

Sheet Bill No.6 Fire fighting Inst.
B2: ITEM | C2: DESCRIPTION | D2: QTY | E2: UNIT | F2: RATE (USHS) | G2: AMOUNT (USHS.)
C3: BILL NO.6
C4: FIRE FIGHTING INSTALLATIONS
C5: Provide all materials, install, connect and set to work the following all as described in the Specifications and Drawings.
C6: All builder's work required for installation shall be provided for in the prices whether or not specifically measured on described below such shall included all chases, mortices, holes, notches, cutting, plugging making good finishes, painting or repainting etc
C7: ELEMENT NO.1
C8: UPPER GROUND FLOOR
C9: Fire Fighting Installations
C10: Portable Fire Extinguishers
B11: A | C11: Carbon Dioxide portable fire extinguisher 5kg as NAFFCO CO2 gas extinguisher Model NC5 or equal approved. | D11: 2 | E11: NO | F11: 280000 | G11: =F11*D11 -> 560000
B12: B | C12: Dry powder portable fire extinguisher 9 kg as NAFFCO ABC powder Model NP9 or equal approved. | D12: 2 | E12: NO | F12: 262500 | G12: =F12*D12 -> 525000
C13: Hose Reel Installations | F13: 0 | G13: =F13*D13 -> 0
B14: C | C14: 75mm Black Seamless Steel SCH40 pipe from water tank to hose reels complete with all accessories. | D14: 6 | E14: LM | F14: 192500 | G14: =F14*D14 -> 1155000
B15: D | C15: 75x32x75mm Tee Black Seamless Steel SCH40 | D15: 2 | E15: NO | F15: 87500 | G15: =F15*D15 -> 175000
B16: E | C16: 750x505mm Reducer Black Seamless Steel SCH40 | D16: 2 | E16: NO | F16: 63000 | G16: =F16*D16 -> 126000
B17: F | C17: 50mm globe valves | D17: 2 | E17: NO | F17: 227500 | G17: =F17*D17 -> 455000
B18: G | C18: 25mm Black Seamless Steel SCH40 pipe complete with all accessories. | D18: 12 | E18: LM | F18: 19250 | G18: =F18*D18 -> 231000
B19: H | C19: Swinging arm automatic semi-rigid hose reel 19mm diameter and 30m long to BSEN 671-1-2001 and BSEN 694-2001 complete with all accessories including wall mounting box, Jet and Spray nozzle and all accessories as NAFFCO Model 19NFH-020A or equal approved. | D19: 2 | E19: NO | F19: 1225000 | G19: =F19*D19 -> 2450000
C20: SPRINKLER SYSTEM
B21: I | C21: 100mm Black Seamless Steel SCH40 pipe complete with all accessories. | D21: 12 | E21: LM | F21: 227500 | G21: =F21*D21 -> 2730000
B22: J | C22: 75mm Black Seamless Steel SCH40 pipe complete with all accessories. | D22: 45 | E22: LM | F22: 192500 | G22: =F22*D22 -> 8662500
B23: K | C23: 65mm Black Seamless Steel SCH40 pipe complete with all accessories. | D23: 6 | E23: LM | F23: 140000 | G23: =F23*D23 -> 840000
B24: L | C24: 50mm Black Seamless Steel SCH40 pipe complete with all accessories. | D24: 24 | E24: LM | F24: 105000 | G24: =F24*D24 -> 2520000
B25: M | C25: 40mm Black Seamless Steel SCH40 pipe complete with all accessories. | D25: 48 | E25: LM | F25: 98000 | G25: =F25*D25 -> 4704000
B26: N | C26: 32mm Black Seamless Steel SCH40 pipe complete with all accessories. | D26: 90 | E26: LM | F26: 84000 | G26: =F26*D26 -> 7560000
B27: A | C27: 100x75mm Reducer Black Seamless Steel SCH40 | D27: 4 | E27: NO | F27: 122500 | G27: =F27*D27 -> 490000
B28: B | C28: 50x50x15mm Tee Black Seamless Steel SCH40 | D28: 60 | E28: NO | F28: 7000 | G28: =F28*D28 -> 420000
B29: C | C29: 75mm Globe Valve | D29: 4 | E29: NO | F29: 490000 | G29: =F29*D29 -> 1960000
B30: D | C30: 50mm globe valves | D30: 8 | E30: NO | F30: 252000 | G30: =F30*D30 -> 2016000
B31: E | C31: Sprinkler heads 78 deg C resistant | D31: 40 | E31: NO | F31: 35000 | G31: =F31*D31 -> 1400000
C34: TO SUMMARY | G34: =SUM(G11:G32) -> 38979500
C35: 6/1/2
C36: BILL NO.6
C37: FIRE FIGHTING INSTALLATIONS
C38: ELEMENT NO.2
C39: FIRST FLOOR
C40: Fire Fighting Installations
C41: Portable Fire Extinguishers
B42: A | C42: Carbon Dioxide portable fire extinguisher 5kg as NAFFCO CO2 gas extinguisher Model NC5 or equal approved. | D42: 2 | E42: NO | F42: 280000 | G42: =F42*D42 -> 560000
B43: B | C43: Dry powder portable fire extinguisher 9 kg as NAFFCO ABC powder Model NP9 or equal approved. | D43: 2 | E43: NO | F43: 262500 | G43: =F43*D43 -> 525000
C44: Hose Reel Installations
B45: C | C45: 100mm Black Seamless Steel SCH40 pipe from water tank to hose reels complete with all accessories. | D45: 6 | E45: LM | F45: 192500 | G45: =F45*D45 -> 1155000
B46: D | C46: 100x32x100mm Tee Black Seamless Steel SCH40 | D46: 2 | E46: NO | F46: 87500 | G46: =F46*D46 -> 175000
B47: E | C47: 100x75mm Reducer Black Seamless Steel SCH40 | D47: 2 | E47: NO | F47: 63000 | G47: =F47*D47 -> 126000
B48: F | C48: 50mm globe valves | D48: 2 | E48: NO | F48: 227500 | G48: =F48*D48 -> 455000
B49: G | C49: 50mm Black Seamless Steel SCH40 pipe complete with all accessories. | D49: 12 | E49: LM | F49: 19250 | G49: =F49*D49 -> 231000
B50: H | C50: Swinging arm automatic semi-rigid hose reel 19mm diameter and 30m long to BSEN 671-1-2001 and BSEN 694-2001 complete with all accessories including wall mounting box, Jet and Spray nozzle and all accessories as NAFFCO Model 19NFH-020M or equal approved. | D50: 2 | E50: NO | F50: 1225000 | G50: =F50*D50 -> 2450000
C51: SPRINKLER SYSTEM
B52: I | C52: 100mm Black Seamless Steel SCH40 pipe complete with all accessories. | D52: 12 | E52: LM | F52: 227500 | G52: =F52*D52 -> 2730000
B53: J | C53: 75mm Black Seamless Steel SCH40 pipe complete with all accessories. | D53: 45 | E53: LM | F53: 192500 | G53: =F53*D53 -> 8662500
B54: K | C54: 65mm Black Seamless Steel SCH40 pipe complete with all accessories. | D54: 6 | E54: LM | F54: 140000 | G54: =F54*D54 -> 840000
B55: L | C55: 50mm Black Seamless Steel SCH40 pipe complete with all accessories. | D55: 24 | E55: LM | F55: 105000 | G55: =F55*D55 -> 2520000
B56: M | C56: 40mm Black Seamless Steel SCH40 pipe complete with all accessories. | D56: 48 | E56: LM | F56: 98000 | G56: =F56*D56 -> 4704000
B57: N | C57: 32mm Black Seamless Steel SCH40 pipe complete with all accessories. | D57: 90 | E57: LM | F57: 84000 | G57: =F57*D57 -> 7560000
B58: O | C58: 100x75mm Reducer Black Seamless Steel SCH40 | D58: 4 | E58: NO | F58: 122500 | G58: =F58*D58 -> 490000
B59: P | C59: 50x50x15mm Tee Black Seamless Steel SCH40 | D59: 60 | E59: NO | F59: 7000 | G59: =F59*D59 -> 420000
B60: Q | C60: 75mm Globe Valve | D60: 4 | E60: NO | F60: 490000 | G60: =F60*D60 -> 1960000
B61: R | C61: 50mm globe valves | D61: 8 | E61: NO | F61: 252000 | G61: =F61*D61 -> 2016000
B62: S | C62: Sprinkler heads 78 deg C resistant | D62: 40 | E62: NO | F62: 35000 | G62: =F62*D62 -> 1400000
C63: TO SUMMARY | G63: =SUM(G42:G62) -> 38979500
C64: 6/2/1
C65: BILL NO.6
C66: FIRE FIGHTING INSTALLATIONS
C67: ELEMENT NO.3
C68: SECOND FLOOR
C69: Fire Fighting Installations
C70: Portable Fire Extinguishers
B71: A | C71: Carbon Dioxide portable fire extinguisher 5kg as NAFFCO CO2 gas extinguisher Model NC5 or equal approved. | D71: 2 | E71: NO | F71: 280000 | G71: =F71*D71 -> 560000
B72: B | C72: Dry powder portable fire extinguisher 9 kg as NAFFCO ABC powder Model NP9 or equal approved. | D72: 2 | E72: NO | F72: 262500 | G72: =F72*D72 -> 525000
C73: Hose Reel Installations
B74: C | C74: 75mm Black Seamless Steel SCH40 pipe from water tank to hose reels complete with all accessories. | D74: 6 | E74: LM | F74: 192500 | G74: =F74*D74 -> 1155000
B75: D | C75: 75x32x75mm Tee Black Seamless Steel SCH40 | D75: 2 | E75: NO | F75: 87500 | G75: =F75*D75 -> 175000
B76: E | C76: 750x505mm Reducer Black Seamless Steel SCH40 | D76: 2 | E76: NO | F76: 63000 | G76: =F76*D76 -> 126000
B77: F | C77: 50mm globe valves | D77: 2 | E77: NO | F77: 227500 | G77: =F77*D77 -> 455000
B78: G | C78: 25mm Black Seamless Steel SCH40 pipe complete with all accessories. | D78: 12 | E78: LM | F78: 19250 | G78: =F78*D78 -> 231000
B79: H | C79: Swinging arm automatic semi-rigid hose reel 19mm diameter and 30m long to BSEN 671-1-2001 and BSEN 694-2001 complete with all accessories including wall mounting box, Jet and Spray nozzle and all accessories as NAFFCO Model 19NFH-020M or equal approved. | D79: 2 | E79: NO | F79: 1225000 | G79: =F79*D79 -> 2450000
C80: SPRINKLER SYSTEM
B81: I | C81: 100mm Black Seamless Steel SCH40 pipe complete with all accessories. | D81: 12 | E81: LM | F81: 227500 | G81: =F81*D81 -> 2730000
B82: J | C82: 75mm Black Seamless Steel SCH40 pipe complete with all accessories. | D82: 45 | E82: LM | F82: 192500 | G82: =F82*D82 -> 8662500
B83: K | C83: 65mm Black Seamless Steel SCH40 pipe complete with all accessories. | D83: 6 | E83: LM | F83: 140000 | G83: =F83*D83 -> 840000
B84: L | C84: 50mm Black Seamless Steel SCH40 pipe complete with all accessories. | D84: 24 | E84: LM | F84: 105000 | G84: =F84*D84 -> 2520000
B85: M | C85: 40mm Black Seamless Steel SCH40 pipe complete with all accessories. | D85: 48 | E85: LM | F85: 98000 | G85: =F85*D85 -> 4704000
B86: N | C86: 32mm Black Seamless Steel SCH40 pipe complete with all accessories. | D86: 90 | E86: LM | F86: 84000 | G86: =F86*D86 -> 7560000
B87: O | C87: 100x75mm Reducer Black Seamless Steel SCH40 | D87: 4 | E87: NO | F87: 122500 | G87: =F87*D87 -> 490000
B88: P | C88: 50x50x15mm Tee Black Seamless Steel SCH40 | D88: 60 | E88: NO | F88: 7000 | G88: =F88*D88 -> 420000
B89: Q | C89: 75mm Globe Valve | D89: 4 | E89: NO | F89: 490000 | G89: =F89*D89 -> 1960000
B90: R | C90: 50mm globe valves | D90: 8 | E90: NO | F90: 252000 | G90: =F90*D90 -> 2016000
B91: S | C91: Sprinkler heads 78 deg C resistant | D91: 40 | E91: NO | F91: 35000 | G91: =F91*D91 -> 1400000
C92: TO SUMMARY | G92: =SUM(G71:G91) -> 38979500
C93: 6/3/1
C94: BILL NO.6
C95: FIRE FIGHTING INSTALLATIONS
C96: ELEMENT NO.4
C97: THIRD FLOOR
C98: Fire Fighting Installations
C99: Portable Fire Extinguishers
B100: A | C100: Carbon Dioxide portable fire extinguisher 5kg as NAFFCO CO2 gas extinguisher Model NC5 or equal approved. | D100: 2 | E100: NO | F100: 280000 | G100: =F100*D100 -> 560000
B101: B | C101: Dry powder portable fire extinguisher 9 kg as NAFFCO ABC powder Model NP9 or equal approved. | D101: 2 | E101: NO | F101: 262500 | G101: =F101*D101 -> 525000
C102: Hose Reel Installations
B103: C | C103: 75mm Black Seamless Steel SCH40 pipe from water tank to hose reels complete with all accessories. | D103: 6 | E103: LM | F103: 192500 | G103: =F103*D103 -> 1155000
...

Sheet Fly Sht. Bill No.7
B2: BILL NO.7
B3: HVAC INSTALLATIONS

Sheet Sum. Bill No.7
B2: ELEMENT | C2: DESCRIPTION | D2: PAGE NO. | E2: AMOUNT (USHS)
C4: ='Fly Sht. Bill No.7'!B2 -> BILL NO.7
C5: ='Fly Sht. Bill No.7'!B3 -> HVAC INSTALLATIONS
C6: SUMMARY
B7: 1 | C7: CONFERENCE HALL | D7: =#REF! -> #REF! | E7: ='Bill No 7 HVAC'!F93 -> 1.5417343e+08
B8: 2 | C8: UPPER GROUND FLOOR | D8: =#REF! -> #REF! | E8: ='Bill No 7 HVAC'!F181 -> 1.3362899e+08
B9: 3 | C9: FIRST FLOOR | D9: =#REF! -> #REF! | E9: ='Bill No 7 HVAC'!F263 -> 1.4855891e+08
B10: 4 | C10: SECOND FLOOR | D10: =#REF! -> #REF! | E10: ='Bill No 7 HVAC'!F330 -> 1.5691649e+08
B11: 6 | C11: THIRD FLOOR | D11: =#REF! -> #REF! | E11: ='Bill No 7 HVAC'!F421 -> 2.2379258e+08
B12: 7 | C12: FOURTH FLOOR | E12: ='Bill No 7 HVAC'!F515 -> 2.2379258e+08
B13: 8 | C13: FIFTH FLOOR | E13: ='Bill No 7 HVAC'!F598 -> 2.2379258e+08
C24: TOTAL BILL NO.7 CARRIED TO MAIN SUMMARY | E24: =SUM(E7:E23) -> 1.2646556e+09
C25: 7/S

Sheet Bill No 7 HVAC
B1: BILLS OF QUANTITIES
A2: Item | B2: Description | C2: Unit | D2: Total Qty | E2: Rate (UGX) | F2: Amount (UGX)
B3: AIR CONDITIONING & VENTILATION
B4: CONFERENCE ROOM
B5: INDOOR UNITS VRF SYSTEM
B6: CEILING CONCEALED DUCT TYPE
B7: Supply Installation Testing and Commissioning of Ceiling Concelead duct type indoor units having
B8: galvanized steel plate casing. The unit shall be insulated with sound absorbing thermal insulation material.
B9: The unit shall be supplied with drain pump with micro processor control.
B10: CEILING CONCEALED DUCT TYPE
A11: A | B11: 14.1kW (48,000Btu/hr) Model: ARNU48GM3A4 CEILING CONCELEAD DUCT AC UNITS | C11: No | D11: 6 | E11: 4100908.5 | F11: =D11*E11 -> 24605451
A12: B | B12: Supply and Installation of Corded remotes with LCD Desplay for VRF indoor units | C12: No | D12: 6 | E12: 360677.97 | F12: =D12*E12 -> 2164067.8
B13: OUTDOOR UNITS OF VRF SYSTEM
B14: Supply Installation Testing and Commissioning of Compact Air Cooled type outdoor units of VRF System
B15: having hermetically sealed scroll type compressors, Dual sensing control and ocean black fin heat exchanger
B16: The unit shall be provided with its own microprocessor control panel with provision for integration with the
B17: building management system for Air-conditioning system.
B18: The VRF System shall have green ref. gas R410A
A19: A | B19: Condensing unit of total cooling coil design capacity 33.6kW, ARUN120LLS5, Input: 8.9kw (3Ph 400V 50Hz). | C19: No | D19: 1 | E19: 23584217 | F19: =D19*E19 -> 23584217
A20: B | B20: Condensing unit of total cooling coil design capacity 56kW, ARUN200LLS5, Input: 14.1kw (3Ph 400V 50Hz). | C20: No | D20: 1 | E20: 27998915 | F20: =D20*E20 -> 27998915
B21: VRV SYSTEM ACCESSORIES
B22: BRANCH DISTRIBUTION REFRIGERENT PIPE JOINTS WITH PRECAST INSULATION
A23: i | B23: ARBLN03321 | C23: No | D23: 2 | E23: 346250.85 | F23: =D23*E23 -> 692501.7
A24: ii | B24: ARBLN07121 | C24: No | D24: 2 | E24: 555444.06 | F24: =D24*E24 -> 1110888.1
A25: iii) | B25: ARBLN14521 | C25: No | D25: 1 | E25: 692501.7 | F25: =D25*E25 -> 692501.7
A26: iv) | B26: ARCNN21 | C26: No | D26: 1 | E26: 483308.47 | F26: =D26*E26 -> 483308.47
B27: REFRIGERATION PIPING & FIRST CHARGE OF REFRIGERANT FOR VRV SYSTEM
A28: i | B28: 9.52mm | C28: LM | D28: 80 | E28: 36480 | F28: =D28*E28 -> 2918400
A29: C | B29: 12.7mm | C29: LM | D29: 5 | E29: 42560 | F29: =D29*E29 -> 212800
A30: ii | B30: 15.88mm | C30: LM | D30: 85 | E30: 54720 | F30: =D30*E30 -> 4651200
A31: iii) | B31: 19.05mm | C31: LM | D31: 25 | E31: 76000 | F31: =D31*E31 -> 1900000
A32: iv) | B32: 22.2mm | C32: LM | D32: 20 | E32: 88160 | F32: =D32*E32 -> 1763200
A33: H | B33: 28.58mm | C33: LM | D33: 10 | E33: 115520 | F33: =D33*E33 -> 1155200
A34: J | B34: 34.9mm | C34: LM | D34: 30 | E34: 173888 | F34: =D34*E34 -> 5216640
B35: Refrigerant
A36: a | B36: Additional Refrigerant of R410A | C36: kg | D36: 20 | E36: 115520 | F36: =D36*E36 -> 2310400
A37: b | B37: Power Cabling to individual Outdoor units with PVC conduits. ( From Isolator to VRV ODU within 5m , The size of the | C37: LM | D37: 10 | E37: 91200 | F37: =D37*E37 -> 912000
B38: cable shall be as per manufacurer's technical requirement )
A39: c | B39: Communication Cable between Outdoor Units & Indoor Units with PVC conduits ( The size of the control cable shall be | C39: LM | D39: 255 | E39: 6779.664 | F39: =D39*E39 -> 1728814.3
B40: as per manufacturer's technical requirement )
B41: Drainage from indoor units
A42: C | B42: 25mm Dia | C42: LM | D42: 60 | E42: 6080 | F42: =D42*E42 -> 364800
A43: D | B43: 32mm Dia | C43: LM | D43: 50 | E43: 9120 | F43: =D43*E43 -> 456000
A44: D | B44: 40mm Dia | C44: LM | D44: 10 | E44: 12160 | F44: =D44*E44 -> 121600
B50: DUCTING AND AIR DISTRIBUTION ACCESSORIES
B51: Supply / Return Air Ducts
B52: Pre-insulated sandwich panels duct work fabricated rigid foamed polyscianurate(PIR) panel sheated with
B53: centeesimal aluminium on bothsides or rigidpolyurethane foam and laminated with centesimal
B54: aluminium foil, 20.5mm thickness Complete with all Reducers,Tees,Bends,Elbows, brackets and
B55: allassociated panel accessories like flange joint and tee connectors, Grillesconnections,
B56: reinforcement section bars, self threading screws, supports for theducts.
B57: 400 x 300mm | C57: LM | D57: 30 | E57: 162305.09 | F57: =D57*E57 -> 4869152.6
B58: 300 x 200mm | C58: LM | D58: 30 | E58: 115932.2 | F58: =D58*E58 -> 3477966
B59: Insulated Flexible duct 200mm | C59: LM | D59: 80 | E59: 91200 | F59: =D59*E59 -> 7296000
B60: Grille Plenum Boxes 2000 x 150mm | C60: Pc | D60: 24 | E60: 498508.47 | F60: =D60*E60 -> 11964203
B61: Supply and installation of Supply air Grille - SAG of extruded aluminium, diffusion and air mixing type,
B62: polyester powder coated aluminium with damper
A63: I | B63: 1000x200mm - Supply Linear Bar Grille. | C63: Pc | D63: 24 | E63: 760000 | F63: =D63*E63 -> 18240000
B64: Supply and installation of Return Air Grille
B65: 600x600 Return Grille. | C65: Pc | D65: 6 | E65: 547200 | F65: =D65*E65 -> 3283200
B93: TOTAL FOR CONFERENCE ROOM. | F93: =SUM(F8:F65) -> 1.5417343e+08
B96: UPPER GROUND FLOOR
B97: INDOOR UNITS VRF SYSTEM
B98: CEILING CASSETTEE TYPE
B99: Supply Installation Testing and Commissioning of Ceiling Cassette type indoor units having galvanized steel
B100: plate casing. The unit shall be insulated with sound absorbing thermal insulation material. The unit shall be
B101: supplied with drain pump with micro processor control.
B102: CEILING CASSETTEE TYPE
A103: A | B103: 3.6kW (12,000Btu/hr) Model: ARNU12GTRB4 CEILING CASSETTE AC UNITS | C103: No | D103: 4 | E103: 2333586.4 | F103: =D103*E103 -> 9334345.8
A104: B | B104: 7.1kW (24,000Btu/hr) Model: ARNU24GTBB4 CEILING CASSETTE AC UNITS | C104: No | D104: 7 | E104: 3062155.9 | F104: =D104*E104 -> 21435092
A105: D | B105: 8.8kW (30,000Btu/hr) Model: ARNU30GTAB4 CEILING CASSETTE AC UNITS | C105: No | D105: 1 | E105: 3480542.4 | F105: =D105*E105 -> 3480542.4
B106: WALL MOUNTED TYPE - SERVEROOM
A107: B | B107: 7.1kW (24,000Btu/hr) Model: ARNU24GSKN4 VRF WALL MOUNTED AC UNITS | C107: No | D107: 1 | E107: 2852962.7 | F107: =D107*E107 -> 2852962.7
A108: E | B108: Standby Split AC Unit Capacity 24,000Btu. | C108: No | D108: 1 | E108: 3272560.7 | F108: =D108*E108 -> 3272560.7
A109: B | B109: Supply and Installation of Corded remotes with LCD Desplay for VRF indoor units | C109: No | D109: 14 | E109: 360677.97 | F109: =D109*E109 -> 5049491.6
B110: PANELS | E110: 0 | F110: =D110*E110 -> 0
A111: C | B111: Cassette Panel for ARNU24GTBB4, ARNU28GTBB4 & ARNU36GTAB4 Model: PT-AAGW0 | C111: No. | D111: 8 | E111: 605938.98 | F111: =D111*E111 -> 4847511.9
B112: Cassette Panel for ARNU12GTRB4 Model: PT-QAGW0 | C112: No. | D112: 4 | E112: 454454.24 | F112: =D112*E112 -> 1817817
B144: OUTDOOR UNITS OF VRF SYSTEM
B145: Supply Installation Testing and Commissioning of Compact Air Cooled type outdoor units of VRF System
B146: having hermetically sealed scroll type compressors, Dual sensing control and ocean black fin heat exchanger
B147: The unit shall be provided with its own microprocessor control panel with provision for integration with the
B148: building management system for Air-conditioning system.
B149: The VRF System shall have green ref. gas R410A
A150: A | B150: Condensing unit of total cooling coil design capacity 33.6kW, ARUN120LLS5, Input: 8.9kw (3Ph 400V 50Hz). | C150: No | D150: 1 | E150: 23584217 | F150: =D150*E150 -> 23584217
A151: B | B151: Ditto but 50.4kW, ARUN180LLS5, Input 12.3kW (3Ph 400V 50Hz). | C151: No | D151: 1 | E151: 26895241 | F151: =D151*E151 -> 26895241
B152: VRV SYSTEM ACCESSORIES
B153: BRANCH DISTRIBUTION REFRIGERENT PIPE JOINTS WITH PRECAST INSULATION
A154: i) | B154: ARBLN01621 | C154: No | D154: 6 | E154: 274115.26 | F154: =D154*E154 -> 1644691.5
A155: ii) | B155: ARBLN03321 | C155: No | D155: 3 | E155: 346250.85 | F155: =D155*E155 -> 1038752.5
A156: iii) | B156: ARBLN07121 | C156: No | D156: 3 | E156: 555444.06 | F156: =D156*E156 -> 1666332.2
A157: iv) | B157: ARCNN21 | C157: No | D157: 1 | E157: 483308.47 | F157: =D157*E157 -> 483308.47
B158: REFRIGERATION PIPING & FIRST CHARGE OF REFRIGERANT FOR VRV SYSTEM
A159: A | B159: 6.35mm | C159: LM | D159: 40 | E159: 30400 | F159: =D159*E159 -> 1216000
A160: B | B160: 9.52mm | C160: LM | D160: 117 | E160: 36480 | F160: =D160*E160 -> 4268160
A161: C | B161: 12.7mm | C161: LM | D161: 40 | E161: 42560 | F161: =D161*E161 -> 1702400
A162: D | B162: 15.88mm | C162: LM | D162: 100 | E162: 54720 | F162: =D162*E162 -> 5472000
A163: E | B163: 19.05mm | C163: LM | D163: 20 | E163: 76000 | F163: =D163*E163 -> 1520000
A164: F | B164: 22.2mm | C164: LM | D164: 10 | E164: 88160 | F164: =D164*E164 -> 881600
A165: H | B165: 28.58mm | C165: LM | D165: 10 | E165: 115520 | F165: =D165*E165 -> 1155200
...

Sheet Fly Sht. Bill No.8
B2: BILL NO.8
B3: LIFT INSTALLATIONS

Sheet Bill No.8 Lift Inst.
B2: ITEM | C2: DESCRIPTION | D2: QTY | E2: UNIT | F2: RATE (USHS) | G2: AMOUNT (USHS.)
C3: BILL NO.8
C4: LIFT INSTALLATIONS
C5: Provide all materials, install, connect and set to work the following all as described in the Specifications and Drawings.
C6: All builder's work required for installation shall be provided for in the prices whether or not specifically measured on described below such shall included all chases, mortices, holes, notches, cutting, plugging making good finishes, painting or repainting etc
C7: ORDINARY PASSENGER LIFTS
C8: The Contractor will inspect site, study drawings, and supply, install, test and commission to the satisfaction of the Engineer, lifts with the following specific details:-
C9: Discrepancies between drawings and specifications must be brought to the attention of the Engineer before supplying the equipment.
C10: The Contractor shall therefore be responsible for supply and installation of a fully operational lift with a certificate from the Government Lift Inspector and a warranty from the manufacturers of at least 1 year.
C11: The lift control shall include an automatic rescue device which shall in case of power failure move the lift car to the next landing and automatically open the doors.
C12: The lift shall be equipped with regenerative braking.
C13: The lift shall be as that made by KONE, or OTIS, or SCHINDLER or MITSUBISHI
C14: The lifts shall include an interface/system/gateway to allow third party to monitor and limited control: Position of lift, up/down, door open/closed, number of persons in lift (overload), VIP reservation of lift, Access Control with Cards, Emergency Stop, Fire etc.
B15: A | C15: Capacity: 1000kg (13 persons). | D15: 2 | E15: NO | F15: 169000000 | G15: =F15*D15 -> 338000000
C16: Number of Stops 7
C17: Number of Opennings 7
C18: Travel: 24 metres (approx.)
C19: Shaft: 2000mm wide by 2300mm deep (inside dimensions)
C20: Drive: Variable Voltage Variable Frequency (VVVF)
C21: Speed: 1.0M/S
C22: Drive: On the side of shaft (machine room-less)
C23: Openings: Double leaf centre telescoping opening, 900mm wide.
C24: Cabin: To be hairline stainless steel
C25: All doors: To be hairline stainless steel
C26: Landing door at Ground floor: In hairline stainless steel
C27: Door architraves: To be in stainless steel
... C31: Power Supply: 415V, 3 phase 50Hz
B32: A | C32: Voltage stabilizer for the lift | D32: 2 | E32: NO | F32: 7350000 | G32: =F32*D32 -> 14700000
B33: B | C33: Builder's works | D33: 2 | E33: ITEM | F33: 1750000 | G33: =F33*D33 -> 3500000
B34: C | C34: Fireman's Switch | D34: 2 | E34: NO | F34: 350000 | G34: =F34*D34 -> 700000
C37: TO SUMMARY | G37: =SUM(G15:G35) -> 356900000
C38: 8/S

Sheet Fly Sht. Bill No.9
B2: BILL NO.9
B3: ICT INSTALLATIONS

Sheet Sum. Bill No.9
B2: ELEMENT | C2: DESCRIPTION | D2: PAGE NO. | E2: AMOUNT (USHS)
C4: ='Fly Sht. Bill No.9'!B2 -> BILL NO.9
C5: ='Fly Sht. Bill No.9'!B3 -> ICT INSTALLATIONS
C6: SUMMARY
B7: 3 | C7: FIRE ALARM SYSTEM | D7: ='Bill No.9 ICT Inst.'!C44 -> 9/3/2 | E7: ='Bill No.9 ICT Inst.'!G43 -> 38685000
B8: 4 | C8: PUBLIC ADDRESS & EVACUATION SYSTEM | D8: ='Bill No.9 ICT Inst.'!C78 -> 9/4/1 | E8: ='Bill No.9 ICT Inst.'!G77 -> 28520000
B9: 5 | C9: AUDIO VISUAL CONFERENCING SYSTEM | D9: ='Bill No.9 ICT Inst.'!C161 -> 9/5/5 | E9: ='Bill No.9 ICT Inst.'!G160 -> 105024000
B10: 6 | C10: SECURITY EQUIPMENT | D10: ='Bill No.9 ICT Inst.'!C195 -> 9/6/1 | E10: ='Bill No.9 ICT Inst.'!G194 -> 8832500
B11: 7 | C11: VOICE & DATA | D11: ='Bill No.9 ICT Inst.'!C236 -> 9/7/3 | E11: ='Bill No.9 ICT Inst.'!G235 -> 150760500
B12: 8 | C12: ACCESS CONTROL | D12: ='Bill No.9 ICT Inst.'!C259 -> 9/8/3 | E12: ='Bill No.9 ICT Inst.'!G258 -> 30635000
B13: 9 | C13: CCTV SYSTEM | D13: ='Bill No.9 ICT Inst.'!C281 -> 9/9/2 | E13: ='Bill No.9 ICT Inst.'!G280 -> 39307500
B14: 10 | C14: IP TV & SIGNAGE SYSTEM | D14: ='Bill No.9 ICT Inst.'!C300 -> 9/10/2 | E14: ='Bill No.9 ICT Inst.'!G299 -> 28502000
C24: TOTAL BILL NO.9 CARRIED TO MAIN SUMMARY | E24: =SUM(E7:E23) -> 430266500
C25: 9/S

Sheet Bill No.9 ICT Inst.
B2: ITEM | C2: DESCRIPTION | D2: QTY | E2: UNIT | F2: RATE (USHS) | G2: AMOUNT (USHS.)
C3: BILL NO.9
C4: ICT INSTALLATIONS
C5: ELEMENT NO.1
C6: Provide all materials, install, connect and set to work the following all as described in the Specifications and Drawings.
C7: All builder's work required for installation shall be provided for in the prices whether or not specifically measured on described below such shall included all chases, mortices, holes, notches, cutting, plugging making good finishes, painting or repainting etc
C8: BILL NO.9
C9: ICT INSTALLATIONS
C10: ELEMENT NO.3
C11: FIRE ALARM SYSTEM
B12: A | C12: 4Loop Analogue addressable Fire Alarm Control Panel Consisting of: | D12: 1 | E12: NO | F12: 6200000 | G12: =F12*D12 -> 6200000
C13: 1 No. Central Processor Unit Module 3-CPU3
C14: 1 No. Network Communications Card, Class A 3-RS485A / MOD-BUS Interface.
C15: 1 No. Liquid Crystal Display Module 3-LCD
C16: 1 No. Primary Power Supply with Local Rail Module, 230V 3-PPS/M-230
C17: 1 No. Single Signature Driver Controller 3-SSDC1
C18: 3 No. Signature Dual Driver Controller 3-SDDC1
C19: 1 No. Chassis Assembly 3-CHAS7
C20: 1 No. Wall box with 1 Chassis Space 3-CAB7B
C21: 1 No. Door for CAB7B Series Wall box 3-CAB7D
C22: 2 No. 40Ah Sealed Lead Acid Battery - 12 Vic 12V40A
C23: 1 No. Battery Cabinet 14" x 18.25"x 7.25" - 40AH max BC-1
C24: 2 No. 6.5 Amp Booster Power Supply BPS6A/230
... C27: Repeater Panel:
B28: B | C28: Repeater Fire Alarm Control Panel each Consists of: | D28: 1 | E28: NO | F28: 1800000 | G28: =F28*D28 -> 1800000
C29: 1 No. Remote LCD Command Module Annunciator 3-LCDANN
C30: 1 No. Surface Wall Box - for Remote LCD Command Module RLCM/B-S
C31: Field Devices:
B32: C | C32: Intelligent Second Generation Photoelectric Smoke Detector SIGA2-PS complete with base and all accessories. | D32: 125 | E32: NO | F32: 105000 | G32: =F32*D32 -> 13125000
B33: D | C33: Intelligent Second Generation Fixed Temperature / Rate-of-Rise Heat Detector - 135F, 15F per minute SIGA2-HRS complete with base and all accessories. | D33: 20 | E33: NO | F33: 145000 | G33: =F33*D33 -> 2900000
B34: E | C34: Manual Pull Station - Double Action, 1-stage (Back Box Not Included) SIGA-278 | D34: 10 | E34: NO | F34: 175000 | G34: =F34*D34 -> 1750000
B35: F | C35: Multi-cd temporal horn-strobe, hi/lo dB - 24V, WHITE G1-HDVM | D35: 10 | E35: NO | F35: 157500 | G35: =F35*D35 -> 1575000
B36: G | C36: Mains Bell | D36: 10 | E36: NO | F36: 210000 | G36: =F36*D36 -> 2100000
B37: H | C37: Signal Input (Riser) Module SIGA-CC1 | D37: 1 | E37: NO | F37: 315000 | G37: =F37*D37 -> 315000
B38: I | C38: Control Relay Module (Interface With Elevators) SIGA-CR | D38: 1 | E38: NO | F38: 210000 | G38: =F38*D38 -> 210000
B39: J | C39: Control Relay Module (Interface With AC) SIGA-CR | D39: 1 | E39: NO | F39: 210000 | G39: =F39*D39 -> 210000
B40: A | C40: Fire Alarm points wired by fire retardant cable 2 core, 1.0mm2 complete with all accessories | D40: =SUM(D12:D39) -> 180 | E40: NO | F40: 35000 | G40: =F40*D40 -> 6300000
B41: B | C41: Programming, Testing, Commissioning, start-up and Handover | D41: 1 | E41: ITEM | F41: 2200000 | G41: =F41*D41 -> 2200000
C43: TO SUMMARY | G43: =SUM(G12:G41) -> 38685000
C44: 9/3/2
C45: BILL NO.9
C46: ICT INSTALLATIONS
C47: ELEMENT NO.4
C48: PUBLIC ADDRESS & EVACUATION SYSTEM
B49: A | C49: 21U data cabinet complete with power supply and fan and mounting rails for patch panels and switches, with glass front door and all accessories. | D49: 1 | E49: NO | F49: 875000 | G49: =F49*D49 -> 875000
B50: B | C50: Voice Alarm system Preamplifier | D50: 1 | E50: NO | F50: 5250000 | G50: =F50*D50 -> 5250000
B51: C | C51: Voice Alarm system Amplifier- VM-3360VACE | D51: 1 | E51: NO | F51: 3675000 | G51: =F51*D51 -> 3675000
B52: D | C52: Emergency Power Supply Unit- VX-2000DSER | D52: 1 | E52: NO | F52: 455000 | G52: =F52*D52 -> 455000
B53: E | C53: Remote Microphone for VM-Series, New Buttons (Successor of RM-200M)- RM-200MS | D53: 1 | E53: NO | F53: 1750000 | G53: =F53*D53 -> 1750000
B54: F | C54: 10W Reflex Horn Speaker for Wide Frequency Response (100V version)- SC-610M | D54: 2 | E54: NO | F54: 262500 | G54: =F54*D54 -> 525000
B55: G | C55: Wall Speaker - Black 6watt 94db 1m/1w - BS-678B | D55: 4 | E55: NO | F55: 140000 | G55: =F55*D55 -> 560000
B56: H | C56: 6 Watt Clip-in Ceiling Speaker 6inch -PC-658R | D56: 48 | E56: NO | F56: 87500 | G56: =F56*D56 -> 4200000
B57: I | C57: Speaker outlets wired by 1 Pair: 16AWG Speaker Bulk Cable (500m) - BC-2S-300M | D57: =SUM(D54:D56) -> 54 | E57: NO | F57: 70000 | G57: =F57*D57 -> 3780000
B58: J | C58: Installation, Consumables & Configuration | D58: 1 | E58: ITEM | F58: 2000000 | G58: =F58*D58 -> 2000000
B59: K | C59: Automated Digital Evacuation Alarm System | D59: 1 | E59: ITEM | F59: 2250000 | G59: =F59*D59 -> 2250000
B60: L | C60: Hearing aid loop in Conference Hall complete. | D60: 1 | E60: SET | F60: 3200000 | G60: =F60*D60 -> 3200000
C77: TO SUMMARY | G77: =SUM(G49:G60) -> 28520000
C78: 9/4/1
C79: BILL NO.9
C80: ICT INSTALLATIONS
C81: ELEMENT NO.5
C83: AUDIO VISUAL CONFERENCING SYSTEM
C84: CONFERENCE - VIDEO
C85: CONFERENCE HALL -AUDIO & VIDEO SYSTEM
C86: DISPLAY SYSTEM
B87: S | C87: NEC P525UL Full HD Projector | Laser | 5200 Lumens | D87: 1 | E87: NO | F87: 7900000 | G87: =F87*D87 -> 7900000
B88: T | C88: Elite Saker Motorized Projector Screen | 135 Inch | 16:9 | 299X168 | D88: 1 | E88: NO | F88: 2375000 | G88: =F88*D88 -> 2375000
B89: U | C89: In Ceiling Projector Screen Box | Length - 3100mm | D89: 1 | E89: NO | F89: 1225000 | G89: =F89*D89 -> 1225000
B90: V | C90: Mount Projector Bracket | D90: 1 | E90: NO | F90: 437500 | G90: =F90*D90 -> 437500
C91: AUDIO SYSTEM
B92: W | C92: Crestron AMP-2210HT 2x210W Commercial Power Amplifier | D92: 1 | E92: NO | F92: 1575000 | G92: =F92*D92 -> 1575000
B93: X | C93: Crestron CS1295 Vector™ Performance Loudspeaker | 12 Inch | 400 Watts | D93: 2 | E93: NO | F93: 3375000 | G93: =F93*D93 -> 6750000
B94: Y | C94: Crestron AMP-2100 Dual-Channel Modular Power Amplifier, 100W/Ch., 4/8Ω | D94: 1 | E94: NO | F94: 875000 | G94: =F94*D94 -> 875000
B95: Z | C95: Crestron IC5-W-T 5.25 Inch In-Ceiling Speaker | Matte White | Pair | D95: 2 | E95: NO | F95: 875000 | G95: =F95*D95 -> 1750000
B96: A | C96: Shure SLX 4 Wireless Microphone Receiver | D96: 2 | E96: NO | F96: 2625000 | G96: =F96*D96 -> 5250000
B97: B | C97: Shure SLX 4 Wireless Bodypack Transmitter | D97: 1 | E97: NO | F97: 1575000 | G97: =F97*D97 -> 1575000
B98: C | C98: Shure WL-185 Lapel Microphone | D98: 2 | E98: NO | F98: 1330000 | G98: =F98*D98 -> 2660000
B99: D | C99: Shure SLX 4 SM58 Wireless Hand Held Microphone Transmitter | D99: 1 | E99: NO | F99: 2520000 | G99: =F99*D99 -> 2520000
B100: E | C100: Shure CVG12D12” (30.5 cm) Gooseneck Microphone with Integrated Desktop Base | D100: 4 | E100: NO | F100: 1680000 | G100: =F100*D100 -> 6720000
B101: D | C101: Crestron DSP-1282 Avia™ 12x8 Digital Signal Processor w/USB Audio, AEC, & Audio Conferencing Interface | D101: 1 | E101: NO | F101: 7475000 | G101: =F101*D101 -> 7475000
C102: WIRELESS COLLABORATION SYSTEM
B103: E | C103: Barco ClickShare CSE-200 | Wireless Presentation Solution | Base station | 2 x Presentation Buttons | 3 Year Warranty | D103: 1 | E103: NO | F103: 3800000 | G103: =F103*D103 -> 3800000
B104: F | C104: ClickShare Tray - Can hold up to 4 Buttons | D104: 1 | E104: NO | F104: 630000 | G104: =F104*D104 -> 630000
C105: CONTROL SYSTEM
B106: G | C106: Crestron CEN-SW-POE-5 5-Port PoE Switch | D106: 1 | E106: NO | F106: 2275000 | G106: =F106*D106 -> 2275000
B107: H | C107: Crestron TSW-760-B-S 7 Inch Full HD Touch Screen | D107: 1 | E107: NO | F107: 3387500 | G107: =F107*D107 -> 3387500
B108: I | C108: Crestron TSW-760-TTK-B-S Tabletop Kit for TSW-760 | D108: 1 | E108: NO | F108: 1085000 | G108: =F108*D108 -> 1085000
C110: SIGNALING SYSTEM
B111: K | C111: Crestron DMPS3-4K-350-C 3-Series® 4K DigitalMedia™ Presentation System 350 | Video Processor | Video Switcher & Matrix | Control Processor | D111: 1 | E111: NO | F111: 8000000 | G111: =F111*D111 -> 8000000
B112: L | C112: Crestron DM-TX-4K-100-C-1G-B-T Floor Box Plate 4K DigitalMedia 8G+® Transmitter 100 | D112: 2 | E112: NO | F112: 2375000 | G112: =F112*D112 -> 4750000
B113: M | C113: Crestron DM-RMC-4KZ-100-C DigitalMedia 8G+® 4K60 4:4:4 HDR Receiver & Room Controller 10 | D113: 2 | E113: NO | F113: 2525000 | G113: =F113*D113 -> 5050000
C117: CABLING
B118: N | C118: Kramer HDMI Flat Cable + Ethernet Support (0.9m) | D118: 10 | E118: LM | F118: 140000 | G118: =F118*D118 -> 1400000
B119: O | C119: Kramer HDMI Flat Cable + Ethernet Support (4.6m) | D119: 4 | E119: LM | F119: 542500 | G119: =F119*D119 -> 2170000
B120: P | C120: Kramer Shielded CAT6 Cabling & Connectors (P/M) | D120: 40 | E120: LM | F120: 12250 | G120: =F120*D120 -> 490000
B121: Q | C121: Kramer BC-2T Balanced Stereo Audio Cable (P/M) | D121: 40 | E121: LM | F121: 14700 | G121: =F121*D121 -> 588000
B122: R | C122: Kramer BC-2S 1.5mm Speaker Cable (P/M) | D122: 50 | E122: LM | F122: 12250 | G122: =F122*D122 -> 612500
B123: S | C123: Kramer 2 Pair Mylar Control Cable (P/M) | D123: 40 | E123: LM | F123: 16800 | G123: =F123*D123 -> 672000
B124: T | C124: Power Cabling & Connectors (P/M) | D124: 30 | E124: LM | F124: 16800 | G124: =F124*D124 -> 504000
B125: U | C125: CATx Cabling & Connectors (P/M) | D125: 30 | E125: LM | F125: 7000 | G125: =F125*D125 -> 210000
...
